Workbook

Sheet Sprint
B6: Sprint Backlog · Sprint 3
B7: Recursos y recurrencia · del 30-09-2026 al 13-10-2026
B8: SIGMA — Sistema Integrado de Gestión de Mantenimiento Industrial · Equipo Código Creativo
B10: Objetivo del Sprint
B11: Que el sistema sepa qué repuestos hay y quién puede ejecutar el trabajo, que el trabajo planificado se genere solo por calendario o por horas de uso, y que la aplicación móvil opere sin conexión.
B15: Ficha del Sprint
B16: Sprint | C16: Sprint 3 de 6
B17: Foco | C17: Recursos y recurrencia
B18: Fechas | C18: Del 30-09-2026 al 13-10-2026 (dos semanas)
B19: Contenido | C19: Repuestos e inventario, terceros y procedimientos, motor de programación.
B20: Product Owner | C20: Catalina Pescio
B21: Scrum Master | C21: Emilio Fuentes
B22: Developer | C22: Bryan Chávez
B23: Origen de las historias | C23: SIGMA_Product_Backlog.docx · Product Backlog priorizado
B25: Capacidad y compromiso
B26: Integrantes del equipo | C26: 3
B27: Horas por integrante y por semana | C27: 40
B28: Semanas del Sprint | C28: 2
B29: Capacidad del Sprint (horas) | C29: =$C$26*$C$27*$C$28
B30: Historias comprometidas | C30: =COUNTA(Historias!$A$6:$A$34)
B31: Puntos de historia comprometidos | C31: =SUM(Historias!$H$6:$H$34)
B32: Horas planificadas en tareas | C32: =SUM(Tareas!$F$6:$F$335)
B33: Uso de la capacidad | C33: =IFERROR($C$32/$C$29,0)
B34: Holgura (horas) | C34: =$C$29-$C$32
B36: Épicas que se entregan en este Sprint
B37: Épica | C37: Nombre de la épica | D37: Historias | E37: Puntos
B38: EP-06 | C38: Repuestos, bodegas e inventario | D38: =COUNTIF(Historias!$B$6:$B$34,$B38) | E38: =SUMIF(Historias!$B$6:$B$34,$B38,Historias!$H$6:$H$34)
B39: EP-07 | C39: Terceros, procedimientos y permisos de trabajo | D39: =COUNTIF(Historias!$B$6:$B$34,$B39) | E39: =SUMIF(Historias!$B$6:$B$34,$B39,Historias!$H$6:$H$34)
B40: EP-08 | C40: Motor de programación | D40: =COUNTIF(Historias!$B$6:$B$34,$B40) | E40: =SUMIF(Historias!$B$6:$B$34,$B40,Historias!$H$6:$H$34)
B41: EP-15 | C41: Aplicación móvil y trabajo sin conexión | D41: =COUNTIF(Historias!$B$6:$B$34,$B41) | E41: =SUMIF(Historias!$B$6:$B$34,$B41,Historias!$H$6:$H$34)
B43: Celdas en amarillo con texto azul: parámetros que el equipo ajusta en el Sprint Planning. El resto se calcula solo. Las historias y su estimación provienen del Product Backlog priorizado; las tareas técnicas son la descomposición del Developer y se refinan en la planificación del Sprint.

Sheet Historias
A1: Sprint 3 · Historias comprometidas
A2: Recursos y recurrencia · del 30-09-2026 al 13-10-2026 · orden por valor de negocio
A5: ID | B5: Épica | C5: Historia de usuario | D5: Como | E5: Quiero | F5: Para | G5: Plataforma | H5: Pts | I5: Valor | J5: Prioridad | K5: Dependencias | L5: Escenarios | M5: Horas plan. | N5: Estado | O5: Responsable | P5: Observaciones
A6: HU-151 | B6: EP-15 | C6: Trabajar sin conexión | D6: técnico de mantenimiento | E6: usar la aplicación completa aunque no tenga señal | F6: no interrumpir el trabajo por una condición que la planta no puede resolver | G6: App | H6: 13 | I6: 100 | J6: Alta | K6: HU-150 | L6: 3 | M6: =SUMIF(Tareas!$B$6:$B$341,$A6,Tareas!$F$6:$F$341) | N6: Movida a Sprint 6 | O6: Bryan Chávez | P6: Movida al Sprint 6 (Sprint Review 1, 15-09-2026). Estado al moverla: Por hacer. Lado servidor listo el 16-09-2026: compuerta 402 (SuscripcionHandler) y descarga por sabana. Lo movil (T-3009/T-3011) es el MVP de la app que trabaja Bryan y no se marca todavia.
A7: HU-073 | B7: EP-08 | C7: Crear una programación por medidor | D7: planificador | E7: programar un trabajo cada cierta cantidad de horas o ciclos | F7: que el mantenimiento se dispare por uso real y no por calendario | G7: Web | H7: 8 | I7: 95 | J7: Alta | K7: HU-042 | L7: 3 | M7: =SUMIF(Tareas!$B$6:$B$341,$A7,Tareas!$F$6:$F$341) | N7: Terminada | O7: Bryan Chávez | P7: Tomada por Bryan el 17-09-2026: disparo por lectura/medición construido (bloque 243) y los 3 criterios OK con evidencia. Pruebas S3 (17-09): #3 OK (medidor por equipo). #1/#2 NO: el disparo por lectura no está construido (pendiente §10.9). DECISIÓN TOMADA 12-09-2026 (Bryan): pme_activo_medidor pasa a NULL (BD/224). Con NULL, el medidor lo aporta cada equipo del plan (Plan_Mantenimiento_Activo.pac_activo_medidor, HU-083). Una programación, cuatro blowers. Falta el disparo por lectura (generador por medidor). || Cerrada el 22-09-2026: 3/3 criterios web verificados con evidencia (SIGMA_Informe_Pruebas_Sprint_3.docx).
A8: HU-076 | B8: EP-08 | C8: Generar las ocurrencias de forma automática | D8: planificador | E8: que el sistema genere solo las ocurrencias futuras | F8: no tener que crear a mano cada mantención del año | G8: Servidor | H8: 8 | I8: 95 | J8: Alta | K8: HU-071, HU-073 | L8: 4 | M8: =SUMIF(Tareas!$B$6:$B$341,$A8,Tareas!$F$6:$F$341) | N8: Terminada | O8: Bryan Chávez | P8: Desbloqueada el 12-09-2026 al existir hitos (HU-081). Generador hecho por Bryan (BD/222); falta el job nocturno que lo dispare con @SOLO_AUTOMATICAS=1. || Cerrada el 22-09-2026: 4/4 criterios web verificados con evidencia (SIGMA_Informe_Pruebas_Sprint_3.docx).
A9: HU-071 | B9: EP-08 | C9: Crear una programación de calendario | D9: planificador | E9: programar un trabajo que se repite según el calendario | F9: cubrir rutinas diarias, semanales, mensuales y anuales | G9: Web | H9: 8 | I9: 90 | J9: Alta | K9: Sin dependencias | L9: 3 | M9: =SUMIF(Tareas!$B$6:$B$341,$A9,Tareas!$F$6:$F$341) | N9: Terminada | O9: Bryan Chávez | P9: Pruebas S3 (17-09): 3 criterios OK (martes/jueves, último día del mes con bisiesto, último viernes). Base de datos y web terminadas. El último día del mes y el último viernes salen correctos, incluido febrero bisiesto. || Cerrada el 22-09-2026: 3/3 criterios web verificados con evidencia (SIGMA_Informe_Pruebas_Sprint_3.docx).
A10: HU-053 | B10: EP-06 | C10: Definir el stock mínimo y máximo de un repuesto | D10: bodeguero | E10: establecer los umbrales de existencia de cada repuesto por bodega | F10: que el sistema avise antes de quedarme sin una pieza crítica | G10: Web | H10: 3 | I10: 85 | J10: Alta | K10: HU-052 | L10: 3 | M10: =SUMIF(Tareas!$B$6:$B$341,$A10,Tareas!$F$6:$F$341) | N10: Terminada | O10: Bryan Chávez | P10: Construida el 31-08-2026: UPS_REPUESTO_BODEGA_STOCK con las tres validaciones del CA1, editable desde la ficha del repuesto. Las alertas se ven en Existencias.aspx. Datos de prueba sembrados el 31-08 (bloque 64). FALTA la verificacion de los criterios, que es de Catalina. || Cerrada el 22-09-2026: 3/3 criterios web verificados con evidencia (SIGMA_Informe_Pruebas_Sprint_3.docx).
A11: HU-055 | B11: EP-06 | C11: Entregar repuestos contra una orden de trabajo | D11: bodeguero | E11: entregar repuestos asociándolos a la orden que los consume | F11: saber cuánto costo de repuestos tuvo cada intervención | G11: Web y App | H11: 5 | I11: 85 | J11: Alta | K11: HU-054 | L11: 3 | M11: =SUMIF(Tareas!$B$6:$B$341,$A11,Tareas!$F$6:$F$341) | N11: Terminada | O11: Bryan Chávez | P11: Construida el 31-08-2026: tipos 2 y 3 del mismo SP. El rechazo por saldo dice la existencia actual, y la devolucion reduce lo consumido de la orden. Datos de prueba sembrados el 31-08 (bloque 64). FALTA la verificacion de los criterios, que es de Catalina. || Cerrada el 22-09-2026: 3/3 criterios web verificados con evidencia (SIGMA_Informe_Pruebas_Sprint_3.docx). La parte móvil se entrega en el Sprint 6.
A12: HU-050 | B12: EP-06 | C12: Administrar el maestro de repuestos | D12: bodeguero | E12: mantener el catálogo de repuestos de la planta | F12: que todos nombren la misma pieza de la misma forma | G12: Web | H12: 5 | I12: 80 | J12: Media | K12: Sin dependencias | L12: 2 | M12: =SUMIF(Tareas!$B$6:$B$341,$A12,Tareas!$F$6:$F$341) | N12: Terminada | O12: Bryan Chávez | P12: Construida el 31-08-2026: SEL/INS/UPD/DEL_REPUESTO (bloque 60), Repuestos.aspx y Repuesto.aspx, GET /repuestos en la API. Nace rep_controla_lote, que faltaba en el modelo. Datos de prueba sembrados el 31-08 (bloque 64). FALTA la verificacion de los criterios, que es de Catalina. || Cerrada el 22-09-2026: 2/2 criterios web verificados con evidencia (SIGMA_Informe_Pruebas_Sprint_3.docx).
A13: HU-056 | B13: EP-06 | C13: Consultar la existencia de un repuesto | D13: usuario de mantenimiento | E13: saber cuántas unidades hay y dónde están | F13: no detener un trabajo por ir a buscar una pieza que no está | G13: Web y App | H13: 3 | I13: 80 | J13: Media | K13: HU-054 | L13: 2 | M13: =SUMIF(Tareas!$B$6:$B$341,$A13,Tareas!$F$6:$F$341) | N13: Terminada | O13: Bryan Chávez | P13: Construida el 31-08-2026: SEL_INVENTARIO_SALDO, Existencias.aspx y su ficha, GET /existencias. Sin cache, a proposito. Datos de prueba sembrados el 31-08 (bloque 64). FALTA la verificacion de los criterios, que es de Catalina. || Cerrada el 22-09-2026: 2/2 criterios web verificados con evidencia (SIGMA_Informe_Pruebas_Sprint_3.docx). La parte móvil se entrega en el Sprint 6.
A14: HU-075 | B14: EP-08 | C14: Definir tolerancias y exclusiones de una programación | D14: planificador | E14: indicar cuánto se puede adelantar o atrasar un trabajo y que días no aplica | F14: que el indicador de cumplimiento refleje la realidad de la planta | G14: Web | H14: 5 | I14: 80 | J14: Media | K14: Sin dependencias | L14: 3 | M14: =SUMIF(Tareas!$B$6:$B$341,$A14,Tareas!$F$6:$F$341) | N14: Terminada | O14: Bryan Chávez | P14: Pruebas S3 (17-09): 3 criterios OK (ventana, feriado desplazado con fecha original, parada de planta). Base de datos y web terminadas. Hizo falta agregar pxc_desplaza para separar la parada de planta (no genera) del feriado (corre la fecha y guarda la original). || Cerrada el 22-09-2026: 3/3 criterios web verificados con evidencia (SIGMA_Informe_Pruebas_Sprint_3.docx).
A15: HU-054 | B15: EP-06 | C15: Registrar el ingreso de repuestos a bodega | D15: bodeguero | E15: registrar la recepción de repuestos con su lote y documento | F15: que la existencia del sistema coincida con la de la estantería | G15: Web y App | H15: 5 | I15: 75 | J15: Media | K15: HU-052 | L15: 2 | M15: =SUMIF(Tareas!$B$6:$B$341,$A15,Tareas!$F$6:$F$341) | N15: Terminada | O15: Bryan Chávez | P15: Construida el 31-08-2026: INS_INVENTARIO_MOVIMIENTO tipo 1, que exige el lote cuando el repuesto lo controla. POST /inventario-movimientos idempotente por uuid. Datos de prueba sembrados el 31-08 (bloque 64). FALTA la verificacion de los criterios, que es de Catalina. || Cerrada el 22-09-2026: 2/2 criterios web verificados con evidencia (SIGMA_Informe_Pruebas_Sprint_3.docx). La parte móvil se entrega en el Sprint 6.
A16: HU-060 | B16: EP-07 | C16: Administrar proveedores | D16: jefe de mantenimiento | E16: mantener el registro de las empresas que prestan servicios | F16: poder sumar al cierre del año cuánto se gastó en cada contratista | G16: Web | H16: 5 | I16: 75 | J16: Media | K16: Sin dependencias | L16: 2 | M16: =SUMIF(Tareas!$B$6:$B$341,$A16,Tareas!$F$6:$F$341) | N16: Terminada | O16: Bryan Chávez | P16: Construida por Bryan (bloque 91). Pruebas S3 (17-09): 2 criterios OK. || Cerrada el 22-09-2026: 2/2 criterios web verificados con evidencia (SIGMA_Informe_Pruebas_Sprint_3.docx).
A17: HU-051 | B17: EP-06 | C17: Definir la compatibilidad de un repuesto | D17: planificador | E17: indicar en qué equipos o modelos aplica cada repuesto | F17: que el técnico no monte una pieza que no corresponde | G17: Web | H17: 3 | I17: 70 | J17: Media | K17: HU-050 | L17: 2 | M17: =SUMIF(Tareas!$B$6:$B$341,$A17,Tareas!$F$6:$F$341) | N17: Terminada | O17: Bryan Chávez | P17: Construida por Bryan (bloque 92). Pruebas S3 (17-09): #1 OK; #2 OK con la regla nueva del bloque 242 (consumo contra OT de un equipo no compatible exige el motivo). || Cerrada el 22-09-2026: 2/2 criterios web verificados con evidencia (SIGMA_Informe_Pruebas_Sprint_3.docx).
... A34: HU-077 | B34: EP-06 | C34: Que el sistema avise lo que encuentra | D34: jefe de mantenimiento | E34: que el sistema detecte solo los problemas de operación y me los notifique | F34: enterarme de un quiebre de stock cuando ocurre y no cuando alguien lo reporta | G34: Web y App | H34: 8 | I34: 95 | J34: Alta | K34: HU-053 | L34: 4 | M34: =SUMIF(Tareas!$B$6:$B$341,$A34,Tareas!$F$6:$F$341) | N34: Terminada | O34: Bryan Chávez | P34: Detectores de los otros modulos listos el 16-09-2026 (bloque 238): quedan las pruebas y documentacion de Catalina (T-3958/T-3959). || Cerrada el 22-09-2026: 4/4 criterios web verificados con evidencia (SIGMA_Informe_Pruebas_Sprint_3.docx). La parte móvil se entrega en el Sprint 6.
C35: Total del Sprint | H35: =SUM(H6:H34) | L35: =SUM(L6:L34) | M35: =SUM(M6:M34)

Sheet Tareas
A1: Sprint 3 · Tareas del Sprint
A2: Descomposición técnica de cada historia comprometida. Se refina en el Sprint Planning y se actualiza en el Daily Scrum.
A5: Tarea | B5: Historia | C5: Título de la historia | D5: Tarea técnica | E5: Tipo | F5: Horas est. | G5: Responsable | H5: Estado | I5: Horas reales | J5: Observaciones
A6: T-3001 | B6: HU-151 | C6: Trabajar sin conexión | D6: Modelo: CREAR la tabla Sincronizacion_Lote — todavía no existe. Columnas, PK, FK a sus padres y columna sin_uuid con índice UNIQUE para que la sincronización no duplique. | E6: Base de datos | F6: 1.5 | G6: Bryan Chávez | H6: Movida a Sprint 6 | J6: Movida al Sprint 6 (Sprint Review 1, 15-09-2026). Estado al moverla: Descartada. Misma decision que en HU-150: la subida es por recurso con uuid (patron 209), no hay lote que persistir. Sincronizacion_Lote no se crea.
A7: T-3002 | B7: HU-151 | C7: Trabajar sin conexión | D7: SP SEL_SINCRONIZACION: lo que baja al teléfono, acotado al usuario y a su planta. | E7: Base de datos | F7: 1.25 | G7: Emilio Fuentes | H7: Movida a Sprint 6 | J7: Movida al Sprint 6 (Sprint Review 1, 15-09-2026). Estado al moverla: Por hacer.
A8: T-3003 | B8: HU-151 | C8: Trabajar sin conexión | D8: SP INS_SINCRONIZACION: recepción de lo que sube el teléfono, idempotente por uuid: el reenvío choca contra el índice en vez de duplicar. | E8: Base de datos | F8: 1.25 | G8: Catalina Pescio | H8: Movida a Sprint 6 | J8: Movida al Sprint 6 (Sprint Review 1, 15-09-2026). Estado al moverla: Por hacer.
A9: T-3004 | B9: HU-151 | C9: Trabajar sin conexión | D9: Datos de prueba en Sincronizacion_Lote para poder ejercitar los criterios de aceptación. | E9: Base de datos | F9: 1.25 | G9: Bryan Chávez | H9: Movida a Sprint 6 | J9: Movida al Sprint 6 (Sprint Review 1, 15-09-2026). Estado al moverla: Descartada. Sin tabla de lotes no hay datos que sembrar.
A10: T-3005 | B10: HU-151 | C10: Trabajar sin conexión | D10: GET /api/sincronizaciones/sync — descarga para el dispositivo, filtrada por usuario y planta. | E10: API | F10: 1.5 | G10: Bryan Chávez | H10: Movida a Sprint 6 | I10: 1.5 | J10: Movida al Sprint 6 (Sprint Review 1, 15-09-2026). Estado al moverla: Terminada. Ya existia como la sabana: GET /sincronizacion (manifiesto) y GET /sincronizacion/{bloque}?desde=, acotada a las plantas del usuario por API_SEL_APP_SABANA_DATOS (bloques 140-234).
A11: T-3006 | B11: HU-151 | C11: Trabajar sin conexión | D11: POST /api/sincronizaciones/sync — subida por lotes, idempotente por uuid. | E11: API | F11: 1.25 | G11: Emilio Fuentes | H11: Movida a Sprint 6 | J11: Movida al Sprint 6 (Sprint Review 1, 15-09-2026). Estado al moverla: Por hacer.
A12: T-3007 | B12: HU-151 | C12: Trabajar sin conexión | D12: Middleware: validar la KEY del cliente contra FNC_SUSCRIPCION_VIGENTE y responder 402 si la suscripción no permite operar. | E12: API | F12: 1.25 | G12: Bryan Chávez | H12: Movida a Sprint 6 | I12: 1.25 | J12: Movida al Sprint 6 (Sprint Review 1, 15-09-2026). Estado al moverla: Terminada. SuscripcionHandler en el pipeline de Web API: con cliente en el token y PUEDE_OPERAR=0 (SEL_SUSCRIPCION_ESTADO_CLIENTE -> FNC_SUSCRIPCION_VIGENTE) responde 402 con el cuerpo estandar; cache 60 s por cliente; registra en Suscripcion_Bloqueo_Log origen API; exentas /sesion, /cliente-usuarios, /mi-perfil.
A13: T-3009 | B13: HU-151 | C13: Trabajar sin conexión | D13: Pantalla Flutter de trabajo sin conexión, usable con guantes: objetivos grandes y sin gestos finos. | E13: Móvil | F13: 0.75 | G13: Bryan Chávez | H13: Movida a Sprint 6 | J13: Movida al Sprint 6 (Sprint Review 1, 15-09-2026). Estado al moverla: Por hacer.
A14: T-3010 | B14: HU-151 | C14: Trabajar sin conexión | D14: Guardar en SQLite local primero y encolar el envío: en terreno no hay señal y el trabajo no se puede perder. | E14: Móvil | F14: 0.75 | G14: Emilio Fuentes | H14: Movida a Sprint 6 | J14: Movida al Sprint 6 (Sprint Review 1, 15-09-2026). Estado al moverla: Por hacer.
A15: T-3011 | B15: HU-151 | C15: Trabajar sin conexión | D15: Reintento de la cola con corte de red a medias, sin duplicar. | E15: Móvil | F15: 0.75 | G15: Bryan Chávez | H15: Movida a Sprint 6 | J15: Movida al Sprint 6 (Sprint Review 1, 15-09-2026). Estado al moverla: Por hacer.
A16: T-3012 | B16: HU-151 | C16: Trabajar sin conexión | D16: Permiso en el servidor: la acción se valida con Token.Puede / ExigirPagina, no escondiendo el botón. Y filtrar por cliente en sesión para que no se vea lo de otra empresa. | E16: Seguridad | F16: 1.5 | G16: Bryan Chávez | H16: Movida a Sprint 6 | I16: 1.5 | J16: Movida al Sprint 6 (Sprint Review 1, 15-09-2026). Estado al moverla: Terminada. La API valida permiso con ExigirPermiso/ExigirCliente y el cliente sale del token, nunca de un parametro; la sabana filtra por las plantas del usuario.
A17: T-3013 | B17: HU-151 | C17: Trabajar sin conexión | D17: Escribir y ejecutar un caso de prueba por cada criterio de aceptación de la historia, y dejar el resultado en la hoja Criterios de aceptación. | E17: Pruebas | F17: 1.75 | G17: Catalina Pescio | H17: Movida a Sprint 6 | J17: Movida al Sprint 6 (Sprint Review 1, 15-09-2026). Estado al moverla: Por hacer.
A18: T-3014 | B18: HU-151 | C18: Trabajar sin conexión | D18: Documentar el endpoint en Swagger y anotar en el MD de estado las decisiones que un tercero no podría deducir del código. | E18: Documentación | F18: 0.75 | G18: Catalina Pescio | H18: Movida a Sprint 6 | J18: Movida al Sprint 6 (Sprint Review 1, 15-09-2026). Estado al moverla: Por hacer.
A19: T-3015 | B19: HU-151 | C19: Trabajar sin conexión | D19: Validación funcional con la Product Owner sobre la pantalla terminada. | E19: Validación | F19: 0.5 | G19: Catalina Pescio | H19: Movida a Sprint 6 | J19: Movida al Sprint 6 (Sprint Review 1, 15-09-2026). Estado al moverla: Por hacer.
A20: T-3016 | B20: HU-073 | C20: Crear una programación por medidor | D20: Modelo: revisar Programacion — columnas, FK e índices. Confirmar el índice único del código dentro del cliente. | E20: Base de datos | F20: 0.75 | G20: Emilio Fuentes | H20: Terminada | J20: Modelo revisado. DECISION PENDIENTE: pme_activo_medidor es NOT NULL y el criterio 3 (un plan, cuatro blowers) necesita que sea nullable.
A21: T-3017 | B21: HU-073 | C21: Crear una programación por medidor | D21: SP INS_PROGRAMACION_MEDIDOR: alta transaccional con las validaciones de negocio de la historia. Devuelve el id creado por OUTPUT. | E21: Base de datos | F21: 0.75 | G21: Bryan Chávez | H21: Terminada | J21: Implementado como UPS_ (upsert) y no como INS_/UPD_ separados: el detalle es 1..1 con la programacion, y separarlos obliga a la pantalla a preguntar antes cual llamar.
A22: T-3018 | B22: HU-073 | C22: Crear una programación por medidor | D22: SP SEL_PROGRAMACION_MEDIDOR: consulta por id y por filtros, para la ficha y el listado. | E22: Base de datos | F22: 0.75 | G22: Bryan Chávez | H22: Terminada | J22: Bloque 104. Calcula ademas el proximo valor de disparo.
A23: T-3019 | B23: HU-073 | C23: Crear una programación por medidor | D23: SP UPD_PROGRAMACION_MEDIDOR: corrección del registro mientras esté en un estado que lo permita. | E23: Base de datos | F23: 0.75 | G23: Bryan Chávez | H23: Terminada | J23: Implementado como UPS_ (upsert) y no como INS_/UPD_ separados: el detalle es 1..1 con la programacion, y separarlos obliga a la pantalla a preguntar antes cual llamar.
A24: T-3020 | B24: HU-073 | C24: Crear una programación por medidor | D24: Datos de prueba en Programacion para poder ejercitar los criterios de aceptación. | E24: Base de datos | F24: 0.75 | G24: Bryan Chávez | H24: Terminada | I24: 0.75 | J24: La decisión del criterio 3 (pme_activo_medidor NULL, BD/224) permite una programación por medidor sin horómetro fijo; el medidor lo pone cada equipo del plan (pac_activo_medidor).
A25: T-3024 | B25: HU-073 | C25: Crear una programación por medidor | D25: Ficha ProgramacionMedidor.aspx: formulario de alta con sus validaciones. | E25: Web | F25: 1.25 | G25: Bryan Chávez | H25: Descartada | J25: Descartada por diseno: se resolvio con UNA ficha y UN listado (T-3239 / T-3240). Programacion es una cabecera con cinco variantes de detalle, no cinco entidades; cinco pantallas serian las mismas secciones comunes copiadas cinco veces.
A26: T-3025 | B26: HU-073 | C26: Crear una programación por medidor | D26: Listado ProgramacionMedidors.aspx con el estado de cada registro. | E26: Web | F26: 1.25 | G26: Bryan Chávez | H26: Descartada | J26: Descartada por diseno: se resolvio con UNA ficha y UN listado (T-3239 / T-3240). Programacion es una cabecera con cinco variantes de detalle, no cinco entidades; cinco pantallas serian las mismas secciones comunes copiadas cinco veces.
A27: T-3026 | B27: HU-073 | C27: Crear una programación por medidor | D27: Permiso en el servidor: la acción se valida con Token.Puede / ExigirPagina, no escondiendo el botón. Y filtrar por cliente en sesión para que no se vea lo de otra empresa. | E27: Seguridad | F27: 1 | G27: Emilio Fuentes | H27: Terminada | J27: Cubierto por T-3241.
A28: T-3027 | B28: HU-073 | C28: Crear una programación por medidor | D28: Escribir y ejecutar un caso de prueba por cada criterio de aceptación de la historia, y dejar el resultado en la hoja Criterios de aceptación. | E28: Pruebas | F28: 1.25 | G28: Catalina Pescio | H28: Terminada | I28: 1.25 | J28: Ejecutadas por Bryan Chávez el 17-09-2026 con evidencia por criterio (Informe de Pruebas Sprint 3, capturas/S3).
A29: T-3028 | B29: HU-073 | C29: Crear una programación por medidor | D29: Documentar el endpoint en Swagger y anotar en el MD de estado las decisiones que un tercero no podría deducir del código. | E29: Documentación | F29: 0.5 | G29: Catalina Pescio | H29: Terminada | I29: 0.5 | J29: Swagger (comentarios XML) y MD de estado al día el 22-09-2026.
A30: T-3029 | B30: HU-073 | C30: Crear una programación por medidor | D30: Validación funcional con la Product Owner sobre la pantalla terminada. | E30: Validación | F30: 0.25 | G30: Catalina Pescio | H30: Terminada | I30: 0.25 | J30: Validado con la Product Owner (registrado el 27-09-2026 por indicación de Bryan Chávez).
A31: T-3030 | B31: HU-076 | C31: Generar las ocurrencias de forma automática | D31: Modelo: revisar Plan_Mantenimiento_Ocurrencia — columnas, FK e índices. Confirmar el índice único del código dentro del cliente. | E31: Base de datos | F31: 1 | G31: Bryan Chávez | H31: Terminada | J31: Revisado. HALLAZGO: pmo_plan_mantenimiento_hito es NOT NULL contra Plan_Mantenimiento_Hito, que es HU-081 del Sprint 4 y esta vacia. Por eso hoy no se puede insertar ninguna ocurrencia.
A32: T-3031 | B32: HU-076 | C32: Generar las ocurrencias de forma automática | D32: SP PLAN_OCURRENCIA: el proceso completo dentro de una transacción, con SET XACT_ABORT ON para que un error no deje datos a medias. | E32: Base de datos | F32: 0.75 | G32: Bryan Chávez | H32: Terminada | I32: 0.75 | J32: BD/222 GEN_PLAN_OCURRENCIAS y GEN_TAREA_OCURRENCIAS: XACT_ABORT, idempotentes, con Programacion_Generacion como marca de agua.
A33: T-3032 | B33: HU-076 | C33: Generar las ocurrencias de forma automática | D33: Reglas de negocio de la historia en el SP, no en la pantalla: la API y la web tienen que obtener el mismo resultado. | E33: Base de datos | F33: 0.75 | G33: Bryan Chávez | H33: Terminada | I33: 0.75 | J33: Reglas en el SP: solo versiones publicadas, programaciones habilitadas, sin duplicar por los dos índices únicos.
A34: T-3033 | B34: HU-076 | C34: Generar las ocurrencias de forma automática | D34: SP SEL_PLAN_OCURRENCIA: consultar el resultado del proceso. | E34: Base de datos | F34: 0.75 | G34: Bryan Chávez | H34: Terminada | I34: 0.75 | J34: SEL_PLAN_CALENDARIO (BD/216) devuelve el resultado; el SP de generación devuelve el resumen por plan e hito.
A35: T-3034 | B35: HU-076 | C35: Generar las ocurrencias de forma automática | D35: Datos de prueba en Plan_Mantenimiento_Ocurrencia para poder ejercitar los criterios de aceptación. | E35: Base de datos | F35: 0.75 | G35: Bryan Chávez | H35: Terminada | I35: 0.75 | J35: _SEMILLA_PLAN_CALENDARIO.sql + generación real sobre PMA-HORNOS-L1.
A36: T-3035 | B36: HU-076 | C36: Generar las ocurrencias de forma automática | D36: POST /api/plan-ocurrencias — dispara el proceso y devuelve su resultado. | E36: API | F36: 1.5 | G36: Bryan Chávez | H36: Terminada | I36: 1.5 | J36: POST /plan-ocurrencias/generar (PlanOcurrenciasController). Probado por HTTP.
A37: T-3036 | B37: HU-076 | C37: Generar las ocurrencias de forma automática | D37: Manejo de errores del SP: cada RAISERROR se traduce a un código HTTP con mensaje, no a un 500 genérico. | E37: API | F37: 1.25 | G37: Bryan Chávez | H37: Terminada | I37: 1.25 | J37: Los RAISERROR llegan como 400 esDeNegocio (plan sin versión publicada verificado).
A38: T-3037 | B38: HU-076 | C38: Generar las ocurrencias de forma automática | D38: Pantalla PlanOcurrencia.aspx: disparar el proceso, mostrar el resultado y dejar constancia de quién lo ejecutó. | E38: Web | F38: 2.25 | G38: Bryan Chávez | H38: Terminada | I38: 2.25 | J38: Sin pantalla suelta: botón «Generar ocurrencias» en la pestaña Calendario del plan y en la tarea, con resultado y usuario.
A39: T-3038 | B39: HU-076 | C39: Generar las ocurrencias de forma automática | D39: Permiso en el servidor: la acción se valida con Token.Puede / ExigirPagina, no escondiendo el botón. Y filtrar por cliente en sesión para que no se vea lo de otra empresa. | E39: Seguridad | F39: 1 | G39: Bryan Chávez | H39: Terminada | I39: 1 | J39: CREAR EDITAR PLANES MANTENIMIENTO en web y API; técnico -> 403 verificado.
A40: T-3039 | B40: HU-076 | C40: Generar las ocurrencias de forma automática | D40: Escribir y ejecutar un caso de prueba por cada criterio de aceptación de la historia, y dejar el resultado en la hoja Criterios de aceptación. | E40: Pruebas | F40: 1.25 | G40: Bryan Chávez | H40: Terminada | I40: 1.25 | J40: Ejecutados por Bryan (ver S4 y MD): horizonte, repetida sin duplicar, manual, programación deshabilitada.
A41: T-3040 | B41: HU-076 | C41: Generar las ocurrencias de forma automática | D41: Documentar el endpoint en Swagger y anotar en el MD de estado las decisiones que un tercero no podría deducir del código. | E41: Documentación | F41: 0.5 | G41: Bryan Chávez | H41: Terminada | I41: 0.5 | J41: XML del controlador + MD.
A42: T-3041 | B42: HU-076 | C42: Generar las ocurrencias de forma automática | D42: Validación funcional con la Product Owner sobre la pantalla terminada. | E42: Validación | F42: 0.25 | G42: Bryan Chávez | H42: Terminada | I42: 0.25 | J42: Pendiente de la PO. · Validado con la Product Owner (registrado el 27-09-2026 por indicación de Bryan Chávez).
A43: T-3042 | B43: HU-071 | C43: Crear una programación de calendario | D43: Modelo: revisar Programacion — columnas, FK e índices. Confirmar el índice único del código dentro del cliente. | E43: Base de datos | F43: 0.75 | G43: Bryan Chávez | H43: Terminada | J43: Modelo revisado: -1 en dia_mes y semana_ordinal significa "el ultimo".
A44: T-3043 | B44: HU-071 | C44: Crear una programación de calendario | D44: SP INS_PROGRAMACION_CALENDARIO: alta transaccional con las validaciones de negocio de la historia. Devuelve el id creado por OUTPUT. | E44: Base de datos | F44: 0.75 | G44: Bryan Chávez | H44: Terminada | J44: Implementado como UPS_ (upsert) y no como INS_/UPD_ separados: el detalle es 1..1 con la programacion, y separarlos obliga a la pantalla a preguntar antes cual llamar.
A45: T-3044 | B45: HU-071 | C45: Crear una programación de calendario | D45: SP SEL_PROGRAMACION_CALENDARIO: consulta por id y por filtros, para la ficha y el listado. | E45: Base de datos | F45: 0.75 | G45: Bryan Chávez | H45: Terminada | J45: Bloque 104. Devuelve los dias en una celda para el combo multiple.
A46: T-3045 | B46: HU-071 | C46: Crear una programación de calendario | D46: SP UPD_PROGRAMACION_CALENDARIO: corrección del registro mientras esté en un estado que lo permita. | E46: Base de datos | F46: 0.75 | G46: Bryan Chávez | H46: Terminada | J46: Implementado como UPS_ (upsert) y no como INS_/UPD_ separados: el detalle es 1..1 con la programacion, y separarlos obliga a la pantalla a preguntar antes cual llamar.
A47: T-3046 | B47: HU-071 | C47: Crear una programación de calendario | D47: Datos de prueba en Programacion para poder ejercitar los criterios de aceptación. | E47: Base de datos | F47: 0.75 | G47: Bryan Chávez | H47: Terminada | J47: Demo semanal, de ultimo dia del mes y de ultimo viernes.
A48: T-3050 | B48: HU-071 | C48: Crear una programación de calendario | D48: Ficha ProgramacionCalendario.aspx: formulario de alta con sus validaciones. | E48: Web | F48: 1.25 | G48: Bryan Chávez | H48: Descartada | J48: Descartada por diseno: se resolvio con UNA ficha y UN listado (T-3239 / T-3240). Programacion es una cabecera con cinco variantes de detalle, no cinco entidades; cinco pantallas serian las mismas secciones comunes copiadas cinco veces.
A49: T-3051 | B49: HU-071 | C49: Crear una programación de calendario | D49: Listado ProgramacionCalendarios.aspx con el estado de cada registro. | E49: Web | F49: 1.25 | G49: Bryan Chávez | H49: Descartada | J49: Descartada por diseno: se resolvio con UNA ficha y UN listado (T-3239 / T-3240). Programacion es una cabecera con cinco variantes de detalle, no cinco entidades; cinco pantallas serian las mismas secciones comunes copiadas cinco veces.
A50: T-3052 | B50: HU-071 | C50: Crear una programación de calendario | D50: Permiso en el servidor: la acción se valida con Token.Puede / ExigirPagina, no escondiendo el botón. Y filtrar por cliente en sesión para que no se vea lo de otra empresa. | E50: Seguridad | F50: 1 | G50: Bryan Chávez | H50: Terminada | J50: Cubierto por T-3241: la seguridad es la de la ficha unica.
A51: T-3053 | B51: HU-071 | C51: Crear una programación de calendario | D51: Escribir y ejecutar un caso de prueba por cada criterio de aceptación de la historia, y dejar el resultado en la hoja Criterios de aceptación. | E51: Pruebas | F51: 1.25 | G51: Catalina Pescio | H51: Terminada | I51: 1.25 | J51: Ejecutadas por Bryan Chávez el 17-09-2026 con evidencia por criterio (Informe de Pruebas Sprint 3, capturas/S3).
A52: T-3054 | B52: HU-071 | C52: Crear una programación de calendario | D52: Documentar el endpoint en Swagger y anotar en el MD de estado las decisiones que un tercero no podría deducir del código. | E52: Documentación | F52: 0.5 | G52: Catalina Pescio | H52: Terminada | I52: 0.5 | J52: Swagger (comentarios XML) y MD de estado al día el 22-09-2026.
A53: T-3055 | B53: HU-071 | C53: Crear una programación de calendario | D53: Validación funcional con la Product Owner sobre la pantalla terminada. | E53: Validación | F53: 0.25 | G53: Catalina Pescio | H53: Terminada | I53: 0.25 | J53: Validado con la Product Owner (registrado el 27-09-2026 por indicación de Bryan Chávez).
A54: T-3056 | B54: HU-053 | C54: Definir el stock mínimo y máximo de un repuesto | D54: Modelo: revisar Inventario_Saldo — columnas, FK e índices. Confirmar el índice único del código dentro del cliente. | E54: Base de datos | F54: 0.5 | G54: Bryan Chávez | H54: Terminada | I54: 0.5 | J54: Modelo revisado. Los umbrales no viven en Inventario_Saldo sino en Repuesto_Bodega_Stock, con UX_RBS_REPUESTO_BODEGA. Saldo y umbral son cosas distintas: uno cambia con cada movimiento, el otro lo define una persona. (31-08-2026)
A55: T-3057 | B55: HU-053 | C55: Definir el stock mínimo y máximo de un repuesto | D55: SP SEL_INVENTARIO_STOCK: listado con filtros opcionales (id, texto, habilitado) y ORDER BY estable. Un solo SP sirve a la grilla y a la ficha. | E55: Base de datos | F55: 0.25 | G55: Bryan Chávez | H55: Terminada | I55: 0.25 | J55: DESVIACION: no es SEL_INVENTARIO_STOCK sino SEL_REPUESTO_BODEGA_STOCK, que es la tabla real. Devuelve BAJO_MINIMO y SOBRE_MAXIMO calculados. (31-08-2026)
A56: T-3058 | B56: HU-053 | C56: Definir el stock mínimo y máximo de un repuesto | D56: SP INS_INVENTARIO_STOCK: alta dentro de transacción. Valida código único por cliente y sella la fecha con FNC_PAIS_HORA. | E56: Base de datos | F56: 0.25 | G56: Bryan Chávez | H56: Terminada | I56: 0.25 | J56: DESVIACION: INS y UPD se unifican en UPS_REPUESTO_BODEGA_STOCK. La fila es "los umbrales de este repuesto EN esta bodega" y tiene indice unico sobre el par: dos procedimientos obligarian a la pantalla a preguntar antes si existe, y esa pregunta se contesta mejor dentro del SP. (31-08-2026)
A57: T-3059 | B57: HU-053 | C57: Definir el stock mínimo y máximo de un repuesto | D57: SP UPD_INVENTARIO_STOCK: edición. Los campos que la ficha no muestra se conservan con ISNULL(@X, columna) para no borrarlos al guardar. | E57: Base de datos | F57: 0.25 | G57: Bryan Chávez | H57: Terminada | I57: 0.25 | J57: DESVIACION: cubierto por UPS_REPUESTO_BODEGA_STOCK. Valida los tres criterios del CA1: el maximo no puede ser menor que el minimo, y el punto de reposicion cae entre los dos. (31-08-2026)
A58: T-3060 | B58: HU-053 | C58: Definir el stock mínimo y máximo de un repuesto | D58: SP DEL_INVENTARIO_STOCK: baja lógica. Rechaza con mensaje si el registro tiene dependientes en vez de dejar huérfanos. | E58: Base de datos | F58: 0.25 | G58: Bryan Chávez | H58: Terminada | I58: 0.25 | J58: DEL_REPUESTO_BODEGA_STOCK, baja logica. (31-08-2026)
A59: T-3061 | B59: HU-053 | C59: Definir el stock mínimo y máximo de un repuesto | D59: Datos de prueba en Inventario_Saldo para poder ejercitar los criterios de aceptación. | E59: Base de datos | F59: 0.25 | G59: Bryan Chávez | H59: Terminada | I59: 0.25 | J59: PENDIENTE: la suite de 18 casos se ejecuto contra la base dentro de transacciones REVERTIDAS, asi que en Inventario_Saldo no quedo nada cargado. Sembrar bodegas y repuestos de verdad es decision del cliente, no del script. Los criterios estan probados; lo que falta es dejar datos para que Catalina recorra las pantallas. · Sembrados el 31-08-2026 (bloque 64) sobre Hamburgo SA / Planta Santiago, todo con prefijo DEMO-: 2 bodegas, 7 ubicaciones, 10 repuestos, 8 umbrales, 2 lotes y 15 movimientos -10 ingresos, 2 consumos, 1 devolucion, 1 ajuste con motivo y 1 traslado-. Elegidos para que se vean TODOS los estados: uno bajo el minimo, uno sobre el maximo, dos sin umbrales y dos que controlan lote. Los 10 saldos cuadran con la suma de sus movimientos.
A60: T-3066 | B60: HU-053 | C60: Definir el stock mínimo y máximo de un repuesto | D60: Listado InventarioStocks.aspx: grilla con búsqueda, filtro de habilitados y botón Nuevo. | E60: Web | F60: 0.25 | G60: Bryan Chávez | H60: Terminada | I60: 0.25 | J60: DESVIACION: no hay InventarioStocks.aspx. Los umbrales se editan desde la ficha del repuesto: no son una entidad que alguien administre por su cuenta, son una propiedad del repuesto en una bodega. La vista de alertas es Existencias.aspx, con su interruptor. (31-08-2026)
A61: T-3067 | B61: HU-053 | C61: Definir el stock mínimo y máximo de un repuesto | D61: Ficha InventarioStock.aspx en RadWindow con las clases sigma-modal-*: campos, validadores y Guardar/Cerrar. | E61: Web | F61: 0.25 | G61: Bryan Chávez | H61: Terminada | I61: 0.25 | J61: DESVIACION: seccion dentro de Repuesto.aspx, por lo mismo. (31-08-2026)
A62: T-3068 | B62: HU-053 | C62: Definir el stock mínimo y máximo de un repuesto | D62: Registrar ambas en Menus con su permiso: sin fila en Menus la pantalla no se abre. | E62: Web | F62: 0.25 | G62: Bryan Chávez | H62: Terminada | I62: 0.25 | J62: Cubierto por los menus de Repuestos y de Existencias. (31-08-2026)
... A75: T-3081 | B75: HU-055 | C75: Entregar repuestos contra una orden de trabajo | D75: Listado InventarioEntregas.aspx con el estado de cada registro. | E75: Web | F75: 0.75 | G75: Bryan Chávez | H75: Terminada | I75: 0.75 | J75: DESVIACION: Movimientos.aspx. (31-08-2026)
A76: T-3082 | B76: HU-055 | C76: Entregar repuestos contra una orden de trabajo | D76: Consumo del endpoint desde la app cuando corresponda. | E76: Móvil | F76: 0.5 | G76: Emilio Fuentes | H76: Movida a Sprint 6 | J76: Movida al Sprint 6 (Sprint Review 1, 15-09-2026). Estado al moverla: Por hacer.
A77: T-3083 | B77: HU-055 | C77: Entregar repuestos contra una orden de trabajo | D77: Permiso en el servidor: la acción se valida con Token.Puede / ExigirPagina, no escondiendo el botón. Y filtrar por cliente en sesión para que no se vea lo de otra empresa. | E77: Seguridad | F77: 0.5 | G77: Bryan Chávez | H77: Terminada | I77: 0.5 | J77: ENTREGAR REPUESTO, para el consumo y la devolucion. (31-08-2026)
A78: T-3084 | B78: HU-055 | C78: Entregar repuestos contra una orden de trabajo | D78: Escribir y ejecutar un caso de prueba por cada criterio de aceptación de la historia, y dejar el resultado en la hoja Criterios de aceptación. | E78: Pruebas | F78: 0.5 | G78: Catalina Pescio | H78: Terminada | I78: 0.5 | J78: Ejecutadas por Bryan Chávez el 17-09-2026 con evidencia por criterio (Informe de Pruebas Sprint 3, capturas/S3).
A79: T-3085 | B79: HU-055 | C79: Entregar repuestos contra una orden de trabajo | D79: Documentar el endpoint en Swagger y anotar en el MD de estado las decisiones que un tercero no podría deducir del código. | E79: Documentación | F79: 0.25 | G79: Catalina Pescio | H79: Terminada | I79: 0.25 | J79: Swagger (comentarios XML) y MD de estado al día el 22-09-2026.
A80: T-3086 | B80: HU-050 | C80: Administrar el maestro de repuestos | D80: Modelo: revisar Repuesto — columnas, FK e índices. Confirmar el índice único del código dentro del cliente. | E80: Base de datos | F80: 0.5 | G80: Bryan Chávez | H80: Terminada | I80: 0.5 | J80: Modelo revisado. Repuesto ya existia; se agrego rep_controla_lote, que faltaba para el criterio 2 de HU-054 -no habia con que saber si un repuesto exige lote-. (31-08-2026)
A81: T-3087 | B81: HU-050 | C81: Administrar el maestro de repuestos | D81: SP SEL_REPUESTO: listado con filtros opcionales (id, texto, habilitado) y ORDER BY estable. Un solo SP sirve a la grilla y a la ficha. | E81: Base de datos | F81: 0.5 | G81: Bryan Chávez | H81: Terminada | I81: 0.5 | J81: SEL_REPUESTO. El filtro busca en codigo, nombre, fabricante Y modelo: eso es el criterio 2 de la historia, el tecnico escribe el numero grabado en la pieza y la encuentra. (31-08-2026)
A82: T-3088 | B82: HU-050 | C82: Administrar el maestro de repuestos | D82: SP INS_REPUESTO: alta dentro de transacción. Valida código único por cliente y sella la fecha con FNC_PAIS_HORA. | E82: Base de datos | F82: 0.5 | G82: Bryan Chávez | H82: Terminada | I82: 0.5 | J82: INS_REPUESTO. Valida codigo unico por cliente y que la unidad exista. (31-08-2026)
A83: T-3089 | B83: HU-050 | C83: Administrar el maestro de repuestos | D83: SP UPD_REPUESTO: edición. Los campos que la ficha no muestra se conservan con ISNULL(@X, columna) para no borrarlos al guardar. | E83: Base de datos | F83: 0.5 | G83: Bryan Chávez | H83: Terminada | I83: 0.5 | J83: UPD_REPUESTO con ISNULL. RECHAZA cambiar la unidad de medida con existencia cargada: 40 litros pasarian a ser 40 unidades sin que nadie los convirtiera. Probado. (31-08-2026)
A84: T-3090 | B84: HU-050 | C84: Administrar el maestro de repuestos | D84: SP DEL_REPUESTO: baja lógica. Rechaza con mensaje si el registro tiene dependientes en vez de dejar huérfanos. | E84: Base de datos | F84: 0.5 | G84: Bryan Chávez | H84: Terminada | I84: 0.5 | J84: DEL_REPUESTO. Rechaza si queda existencia y arrastra sus umbrales, que si no dejarian alertas vivas de algo que ya no se usa. (31-08-2026)
A85: T-3091 | B85: HU-050 | C85: Administrar el maestro de repuestos | D85: Datos de prueba en Repuesto para poder ejercitar los criterios de aceptación. | E85: Base de datos | F85: 0.25 | G85: Bryan Chávez | H85: Terminada | I85: 0.25 | J85: PENDIENTE: la suite de 18 casos se ejecuto contra la base dentro de transacciones REVERTIDAS, asi que en Repuesto no quedo nada cargado. Sembrar bodegas y repuestos de verdad es decision del cliente, no del script. Los criterios estan probados; lo que falta es dejar datos para que Catalina recorra las pantallas. · Sembrados el 31-08-2026 (bloque 64) sobre Hamburgo SA / Planta Santiago, todo con prefijo DEMO-: 2 bodegas, 7 ubicaciones, 10 repuestos, 8 umbrales, 2 lotes y 15 movimientos -10 ingresos, 2 consumos, 1 devolucion, 1 ajuste con motivo y 1 traslado-. Elegidos para que se vean TODOS los estados: uno bajo el minimo, uno sobre el maximo, dos sin umbrales y dos que controlan lote. Los 10 saldos cuadran con la suma de sus movimientos.
A86: T-3096 | B86: HU-050 | C86: Administrar el maestro de repuestos | D86: Listado Repuestos.aspx: grilla con búsqueda, filtro de habilitados y botón Nuevo. | E86: Web | F86: 0.5 | G86: Bryan Chávez | H86: Terminada | I86: 0.5 | J86: Repuestos.aspx. (31-08-2026)
A87: T-3097 | B87: HU-050 | C87: Administrar el maestro de repuestos | D87: Ficha Repuesto.aspx en RadWindow con las clases sigma-modal-*: campos, validadores y Guardar/Cerrar. | E87: Web | F87: 0.5 | G87: Bryan Chávez | H87: Terminada | I87: 0.5 | J87: Repuesto.aspx con sigma-modal-*, incluyendo los umbrales por bodega (HU-053). (31-08-2026)
A88: T-3098 | B88: HU-050 | C88: Administrar el maestro de repuestos | D88: Registrar ambas en Menus con su permiso: sin fila en Menus la pantalla no se abre. | E88: Web | F88: 0.5 | G88: Bryan Chávez | H88: Terminada | I88: 0.5 | J88: Menus 2113 y 2117, con VER REPUESTOS. (31-08-2026)
... A98: T-3108 | B98: HU-056 | C98: Consultar la existencia de un repuesto | D98: Pantalla InventarioSaldo.aspx de solo lectura: filtros arriba, grilla y exportación. | E98: Web | F98: 0.75 | G98: Bryan Chávez | H98: Terminada | I98: 0.75 | J98: DESVIACION: Existencias.aspx (listado, con interruptor de alertas) y Existencia.aspx (la ficha del CA1: un repuesto, sus bodegas, ubicacion, umbrales y ultimos movimientos). (31-08-2026)
A99: T-3109 | B99: HU-056 | C99: Consultar la existencia de un repuesto | D99: Consumo del endpoint desde la app cuando corresponda. | E99: Móvil | F99: 0.5 | G99: Bryan Chávez | H99: Movida a Sprint 6 | J99: Movida al Sprint 6 (Sprint Review 1, 15-09-2026). Estado al moverla: Por hacer.
A100: T-3110 | B100: HU-056 | C100: Consultar la existencia de un repuesto | D100: Permiso en el servidor: la acción se valida con Token.Puede / ExigirPagina, no escondiendo el botón. Y filtrar por cliente en sesión para que no se vea lo de otra empresa. | E100: Seguridad | F100: 0.25 | G100: Bryan Chávez | H100: Terminada | I100: 0.25 | J100: VER EXISTENCIAS, ambito AMBOS. (31-08-2026)
A101: T-3111 | B101: HU-056 | C101: Consultar la existencia de un repuesto | D101: Escribir y ejecutar un caso de prueba por cada criterio de aceptación de la historia, y dejar el resultado en la hoja Criterios de aceptación. | E101: Pruebas | F101: 0.25 | G101: Catalina Pescio | H101: Terminada | I101: 0.25 | J101: Ejecutadas por Bryan Chávez el 17-09-2026 con evidencia por criterio (Informe de Pruebas Sprint 3, capturas/S3).
A102: T-3112 | B102: HU-056 | C102: Consultar la existencia de un repuesto | D102: Documentar el endpoint en Swagger y anotar en el MD de estado las decisiones que un tercero no podría deducir del código. | E102: Documentación | F102: 0.25 | G102: Catalina Pescio | H102: Terminada | I102: 0.25 | J102: Swagger (comentarios XML) y MD de estado al día el 22-09-2026.
A103: T-3113 | B103: HU-075 | C103: Definir tolerancias y exclusiones de una programación | D103: Modelo: revisar Programacion_Exclusion — columnas, FK e índices. Confirmar el índice único del código dentro del cliente. | E103: Base de datos | F103: 0.5 | G103: Emilio Fuentes | H103: Terminada | J103: Modelo revisado: faltaba distinguir excluir de desplazar (ver T-3963).
A104: T-3114 | B104: HU-075 | C104: Definir tolerancias y exclusiones de una programación | D104: SP SEL_PROGRAMACION_EXCLUSION: listado con filtros opcionales (id, texto, habilitado) y ORDER BY estable. Un solo SP sirve a la grilla y a la ficha. | E104: Base de datos | F104: 0.5 | G104: Catalina Pescio | H104: Terminada | J104: Bloque 105.
A105: T-3115 | B105: HU-075 | C105: Definir tolerancias y exclusiones de una programación | D105: SP INS_PROGRAMACION_EXCLUSION: alta dentro de transacción. Valida código único por cliente y sella la fecha con FNC_PAIS_HORA. | E105: Base de datos | F105: 0.5 | G105: Bryan Chávez | H105: Terminada | J105: Bloque 105. Rechaza exclusiones superpuestas.
A106: T-3116 | B106: HU-075 | C106: Definir tolerancias y exclusiones de una programación | D106: SP UPD_PROGRAMACION_EXCLUSION: edición. Los campos que la ficha no muestra se conservan con ISNULL(@X, columna) para no borrarlos al guardar. | E106: Base de datos | F106: 0.5 | G106: Emilio Fuentes | H106: Terminada | J106: Bloque 105.
A107: T-3117 | B107: HU-075 | C107: Definir tolerancias y exclusiones de una programación | D107: SP DEL_PROGRAMACION_EXCLUSION: baja lógica. Rechaza con mensaje si el registro tiene dependientes en vez de dejar huérfanos. | E107: Base de datos | F107: 0.5 | G107: Catalina Pescio | H107: Terminada | J107: Bloque 105. Baja logica: la exclusion explica un hueco en el plan.
A108: T-3118 | B108: HU-075 | C108: Definir tolerancias y exclusiones de una programación | D108: Datos de prueba en Programacion_Exclusion para poder ejercitar los criterios de aceptación. | E108: Base de datos | F108: 0.25 | G108: Bryan Chávez | H108: Terminada | J108: Una parada de planta y un feriado, para los criterios 2 y 3.
A109: T-3123 | B109: HU-075 | C109: Definir tolerancias y exclusiones de una programación | D109: Listado ProgramacionExclusions.aspx: grilla con búsqueda, filtro de habilitados y botón Nuevo. | E109: Web | F109: 0.5 | G109: Emilio Fuentes | H109: Descartada | J109: Descartada por diseno: las exclusiones se administran dentro de la ficha de la programacion, que es donde tienen sentido.
A110: T-3124 | B110: HU-075 | C110: Definir tolerancias y exclusiones de una programación | D110: Ficha ProgramacionExclusion.aspx en RadWindow con las clases sigma-modal-*: campos, validadores y Guardar/Cerrar. | E110: Web | F110: 0.5 | G110: Bryan Chávez | H110: Descartada | J110: Descartada por diseno: las exclusiones se administran dentro de la ficha de la programacion, que es donde tienen sentido.
A111: T-3125 | B111: HU-075 | C111: Definir tolerancias y exclusiones de una programación | D111: Registrar ambas en Menus con su permiso: sin fila en Menus la pantalla no se abre. | E111: Web | F111: 0.5 | G111: Emilio Fuentes | H111: Terminada | J111: Menu Mantenimiento > Programaciones, con Menu_Funcion y cuatro perfiles.
A112: T-3126 | B112: HU-075 | C112: Definir tolerancias y exclusiones de una programación | D112: Permiso en el servidor: la acción se valida con Token.Puede / ExigirPagina, no escondiendo el botón. Y filtrar por cliente en sesión para que no se vea lo de otra empresa. | E112: Seguridad | F112: 0.5 | G112: Bryan Chávez | H112: Terminada | J112: Cubierto por T-3241.
A113: T-3127 | B113: HU-075 | C113: Definir tolerancias y exclusiones de una programación | D113: Escribir y ejecutar un caso de prueba por cada criterio de aceptación de la historia, y dejar el resultado en la hoja Criterios de aceptación. | E113: Pruebas | F113: 0.5 | G113: Catalina Pescio | H113: Terminada | I113: 0.5 | J113: Ejecutadas por Bryan Chávez el 17-09-2026 con evidencia por criterio (Informe de Pruebas Sprint 3, capturas/S3).
A114: T-3128 | B114: HU-075 | C114: Definir tolerancias y exclusiones de una programación | D114: Documentar el endpoint en Swagger y anotar en el MD de estado las decisiones que un tercero no podría deducir del código. | E114: Documentación | F114: 0.25 | G114: Catalina Pescio | H114: Terminada | I114: 0.25 | J114: Swagger (comentarios XML) y MD de estado al día el 22-09-2026.
A115: T-3129 | B115: HU-054 | C115: Registrar el ingreso de repuestos a bodega | D115: Modelo: revisar Inventario_Movimiento — columnas, FK e índices. Confirmar el índice único del código dentro del cliente. | E115: Base de datos | F115: 0.5 | G115: Bryan Chávez | H115: Terminada | I115: 0.5 | J115: Modelo revisado. Inventario_Movimiento e Inventario_Saldo con UX_ISA_REPUESTO_BODEGA. (31-08-2026)
A116: T-3130 | B116: HU-054 | C116: Registrar el ingreso de repuestos a bodega | D116: SP INS_INVENTARIO_INGRESO: alta transaccional con las validaciones de negocio de la historia. Devuelve el id creado por OUTPUT. | E116: Base de datos | F116: 0.5 | G116: Bryan Chávez | H116: Terminada | I116: 0.5 | J116: DESVIACION: no es INS_INVENTARIO_INGRESO. Es INS_INVENTARIO_MOVIMIENTO, UNO SOLO para los ocho tipos. Lo dificil de un inventario no es insertar la fila, es que Inventario_Saldo no se despegue nunca de Inventario_Movimiento; con seis procedimientos hay seis copias de esa logica y basta que una se olvide de tocar el saldo. Exige el lote cuando el repuesto lo controla (CA2). Probado: ingreso de 10 deja saldo 10. (31-08-2026)
A117: T-3131 | B117: HU-054 | C117: Registrar el ingreso de repuestos a bodega | D117: SP SEL_INVENTARIO_INGRESO: consulta por id y por filtros, para la ficha y el listado. | E117: Base de datos | F117: 0.5 | G117: Bryan Chávez | H117: Terminada | I117: 0.5 | J117: DESVIACION: SEL_INVENTARIO_MOVIMIENTO, con @TIPO para acotar a los ingresos. (31-08-2026)
A118: T-3132 | B118: HU-054 | C118: Registrar el ingreso de repuestos a bodega | D118: SP UPD_INVENTARIO_INGRESO: corrección del registro mientras esté en un estado que lo permita. | E118: Base de datos | F118: 0.5 | G118: Bryan Chávez | H118: Terminada | I118: 0.5 | J118: DESVIACION: un movimiento NO se edita: es el registro de algo que paso. Si queda mal se corrige con otro movimiento en sentido contrario, que es lo que deja rastro de la correccion. No se construye UPD_INVENTARIO_INGRESO. (31-08-2026)
A119: T-3133 | B119: HU-054 | C119: Registrar el ingreso de repuestos a bodega | D119: Datos de prueba en Inventario_Movimiento para poder ejercitar los criterios de aceptación. | E119: Base de datos | F119: 0.5 | G119: Bryan Chávez | H119: Terminada | I119: 0.5 | J119: PENDIENTE: la suite de 18 casos se ejecuto contra la base dentro de transacciones REVERTIDAS, asi que en Inventario_Movimiento no quedo nada cargado. Sembrar bodegas y repuestos de verdad es decision del cliente, no del script. Los criterios estan probados; lo que falta es dejar datos para que Catalina recorra las pantallas. · Sembrados el 31-08-2026 (bloque 64) sobre Hamburgo SA / Planta Santiago, todo con prefijo DEMO-: 2 bodegas, 7 ubicaciones, 10 repuestos, 8 umbrales, 2 lotes y 15 movimientos -10 ingresos, 2 consumos, 1 devolucion, 1 ajuste con motivo y 1 traslado-. Elegidos para que se vean TODOS los estados: uno bajo el minimo, uno sobre el maximo, dos sin umbrales y dos que controlan lote. Los 10 saldos cuadran con la suma de sus movimientos.
A120: T-3134 | B120: HU-054 | C120: Registrar el ingreso de repuestos a bodega | D120: POST /api/inventario-ingresos — alta. Idempotente por uuid para que un reintento del teléfono no cree dos registros. | E120: API | F120: 0.75 | G120: Bryan Chávez | H120: Terminada | I120: 0.75 | J120: POST /inventario-movimientos, idempotente por uuid. Probado: dos llamadas con el mismo uuid devuelven el mismo id y el saldo se mueve UNA vez. Es la unica defensa real contra el doble consumo cuando el telefono reintenta. (31-08-2026)
A121: T-3135 | B121: HU-054 | C121: Registrar el ingreso de repuestos a bodega | D121: GET /api/inventario-ingresos/{id} y GET /api/inventario-ingresos — detalle y listado. | E121: API | F121: 0.5 | G121: Bryan Chávez | H121: Terminada | I121: 0.5 | J121: GET /inventario-movimientos y GET /inventario-movimientos/{id}. (31-08-2026)
A122: T-3136 | B122: HU-054 | C122: Registrar el ingreso de repuestos a bodega | D122: Mapeo DTO ↔ entidad y validación del cuerpo antes de llamar al SP. | E122: API | F122: 0.5 | G122: Bryan Chávez | H122: Terminada | I122: 0.5 | J122: MovimientoAltaDto e InventarioMovimientoDto, con validacion del cuerpo antes del SP. (31-08-2026)
A123: T-3137 | B123: HU-054 | C123: Registrar el ingreso de repuestos a bodega | D123: Ficha InventarioIngreso.aspx: formulario de alta con sus validaciones. | E123: Web | F123: 0.75 | G123: Bryan Chávez | H123: Terminada | I123: 0.75 | J123: DESVIACION: Movimiento.aspx, una sola ficha para ingreso, entrega, devolucion, ajuste y traslado. Los campos aparecen segun el tipo: el lote solo al ingresar, la orden solo al consumir, el destino solo al trasladar, el motivo obligatorio solo al ajustar. (31-08-2026)
...

Sheet Criterios de aceptación
A1: Sprint 3 · Criterios de aceptación
A2: Definición contractual de terminado de cada historia. Todos deben pasar para dar la historia por hecha.
A5: Historia | B5: Título de la historia | C5: N.º | D5: Escenario | E5: Criterio (Dado / Cuando / Entonces) | F5: Verificado
A6: HU-151 | B6: Trabajar sin conexión | C6: 1 | D6: Turno completo sin señal | E6: Dado que estoy sin conexión desde que entré a la planta Cuando escaneo códigos, abro órdenes, ejecuto checklists, dicto observaciones y tomo fotografías Entonces todo funciona sin ningún mensaje de error de red | F6: Sprint 6
A7: HU-151 | B7: Trabajar sin conexión | C7: 2 | D7: Indicador permanente | E7: Cuando estoy sin conexión Entonces un indicador visible muestra el estado y la cantidad de cambios pendientes | F7: Sprint 6
A8: HU-151 | B8: Trabajar sin conexión | C8: 3 | D8: Espacio disponible | E8: Cuando el almacenamiento del dispositivo está por agotarse Entonces se advierte antes de que impida seguir capturando evidencias | F8: Sprint 6
A9: HU-073 | B9: Crear una programación por medidor | C9: 1 | D9: Disparo por horas | E9: Dado un plan cada 500 horas y un horómetro en 8.200 al cierre del hito anterior Cuando se registra una lectura de 8.700 horas Entonces se genera la ocurrencia correspondiente | F9: Sí
A10: HU-073 | B10: Crear una programación por medidor | C10: 2 | D10: Aviso anticipado | E10: Dado un plan cada 500 horas con aviso 50 horas antes Cuando se registra una lectura de 8.655 horas Entonces se genera una alerta de medidor próximo a mantenimiento Y la alerta no genera una orden de trabajo por si sola | F10: Sí
A11: HU-073 | B11: Crear una programación por medidor | C11: 3 | D11: Un horómetro por equipo | E11: Dado un plan aplicado a cuatro blowers identicos Entonces cada equipo dispara según su propio horómetro Y no se requiere crear cuatro planes | F11: Sí
A12: HU-076 | B12: Generar las ocurrencias de forma automática | C12: 1 | D12: Generación por horizonte | E12: Cuando el proceso automático se ejecuta Entonces genera las ocurrencias de los próximos 90 días Y avanza la marca de agua hasta la fecha generada | F12: Sí
A13: HU-076 | B13: Generar las ocurrencias de forma automática | C13: 2 | D13: Ejecución repetida | E13: Cuando el proceso automático se ejecuta dos veces seguidas Entonces la segunda ejecución no genera ocurrencias duplicadas | F13: Sí
A14: HU-076 | B14: Generar las ocurrencias de forma automática | C14: 3 | D14: Generación manual | E14: Cuando solicito generar ocurrencias de una programación específica Entonces se generan de inmediato sin esperar al proceso automático | F14: Sí
A15: HU-076 | B15: Generar las ocurrencias de forma automática | C15: 4 | D15: Programación deshabilitada | E15: Dado que deshabilito una programación Entonces deja de generar ocurrencias nuevas Y las ya generadas se conservan La marca de agua es lo que hace idempotente la generación. Sin ella, dos ejecuciones del proceso crean la misma ocurrencia dos veces y el técnico ve trabajo duplicado. | F15: Sí
A16: HU-071 | B16: Crear una programación de calendario | C16: 1 | D16: Recurrencia semanal | E16: Cuando defino repetición semanal los martes y jueves Entonces se generan ocurrencias en cada martes y jueves del periodo de vigencia | F16: Sí
A17: HU-071 | B17: Crear una programación de calendario | C17: 2 | D17: Último día del mes | E17: Cuando defino repetición mensual el último día del mes Entonces la ocurrencia de febrero cae el 28 o el 29 según corresponda Y la de enero cae el 31 | F17: Sí
... A81: HU-077 | B81: Que el sistema avise lo que encuentra | C81: 4 | D81: La app recibe lo mismo | E81: Cuando la app consulta GET /alertas y /alertas/resumen Entonces recibe las mismas alertas y el mismo contador que la web | F81: Sí

Sheet Definition of Done
A1: Definition of Done
A2: Se aplica por igual a toda historia de todo Sprint. Una historia que no cumple los diez criterios no está terminada.
A4: N.º | B4: Dimensión | C4: Criterio | D4: Cumple
A5: 1 | B5: Funcionalidad | C5: Todos los criterios de aceptación de la historia se verifican y pasan. | D5: No
A6: 2 | B6: Seguridad | C6: Los permisos se validan en el servidor y no solamente ocultando controles en la interfaz. | D6: No
A7: 3 | B7: Terreno | C7: Si la historia involucra la aplicación móvil, funciona sin conexión y sincroniza sin generar registros duplicados. | D7: No
A8: 4 | B8: Multicliente | C8: Ningún dato de otro cliente resulta accesible. Se verifica de forma explícita con dos clientes cargados. | D8: No
A9: 5 | B9: Idioma | C9: Los textos están en español de Chile y no hay cadenas de texto fijas en el código. | D9: No
A10: 6 | B10: Despliegue | C10: La funcionalidad está desplegada en el ambiente de demostración con datos de prueba. | D10: No
A11: 7 | B11: Usabilidad | C11: Una persona ajena al equipo la utiliza sin explicación previa y completa la tarea. | D11: No
A12: 8 | B12: Pruebas | C12: Existe al menos un caso de prueba por escenario de aceptación y todos se ejecutan con resultado correcto antes de dar la historia por terminada. | D12: No
A13: 9 | B13: Revisión de código | C13: El código fue revisado por un integrante distinto de quien lo escribió, está integrado en la rama principal y no deja advertencias del compilador. | D13: No
A14: 10 | B14: Documentación | C14: El endpoint queda documentado en Swagger, el cambio en el modelo de datos queda registrado y la historia queda cerrada en el Sprint Backlog. | D14: No
A16: El criterio 7 es el más exigente y el más útil: una pantalla que necesita a su desarrollador al lado para ser usada no está terminada, está demostrada. El detalle completo, con la forma de verificar cada criterio y quién lo verifica, está en el documento SIGMA_Definition_of_Done.docx.
