Workbook

Sheet Resumen
B6: Evidencia de Daily Scrum
B7: SIGMA — Sistema Integrado de Gestión de Mantenimiento Industrial
B8: Bitácora de avance, impedimentos y próximos pasos · Equipo Código Creativo
B10: Ficha del artefacto
B11: Evento Scrum | C11: Daily Scrum · quince minutos, misma hora y mismo lugar
B12: Periodicidad | C12: Todos los días hábiles del Sprint
B13: Participantes | C13: Equipo completo: Bryan Chávez, Catalina Pescio, Emilio Fuentes
B14: Facilita | C14: Emilio Fuentes (Scrum Master)
B15: Cobertura | C15: Sprints 1 a 6 · del 02-09-2026 al 24-11-2026 · semanas académicas S5 a S17
B16: Formato de entrega | C16: Bitácora en Excel, compatible con el tablero de GitHub Projects
B17: Versión | C17: 1.3 · 12-10-2026 · Sprints 1 a 5 con registro diario; HU-142 y HU-143 de Catalina En revisión
B19: Indicadores de la bitácora
B20: Dailies planificados | C20: Participaciones esperadas | D20: Participaciones registradas | E20: Cumplimiento | F20: Impedimentos registrados | G20: Impedimentos abiertos | H20: Impedimentos resueltos
B21: =58 | C21: =COUNTA(Bitácora!$A$5:$A$181) | D21: =COUNTIF(Bitácora!$P$5:$P$181,"Sí") | E21: =IFERROR(COUNTIF(Bitácora!$P$5:$P$181,"Sí")/COUNTA(Bitácora!$A$5:$A$181),0) | F21: =COUNTA(Impedimentos!$B$5:$B$64) | G21: =COUNTIF(Impedimentos!$J$5:$J$64,"Abierto")+COUNTIF(Impedimentos!$J$5:$J$64,"En gestión")+COUNTIF(Impedimentos!$J$5:$J$64,"Escalado") | H21: =COUNTIF(Impedimentos!$J$5:$J$64,"Resuelto")
B23: Detalle por Sprint
B24: Sprint | C24: Foco | D24: Desde | E24: Hasta | F24: Dailies | G24: Participaciones registradas | H24: Cumplimiento | I24: Impedimentos
B25: Sprint 1 | C25: Fundaciones | D25: 46267 | E25: 46280 | F25: 10 | G25: =COUNTIFS(Bitácora!$F$5:$F$181,$B25,Bitácora!$P$5:$P$181,"Sí") | H25: =IFERROR($G25/COUNTIF(Bitácora!$F$5:$F$181,$B25),0) | I25: =COUNTIF(Impedimentos!$C$5:$C$64,$B25)
B26: Sprint 2 | C26: Activos | D26: 46281 | E26: 46294 | F26: 9 | G26: =COUNTIFS(Bitácora!$F$5:$F$181,$B26,Bitácora!$P$5:$P$181,"Sí") | H26: =IFERROR($G26/COUNTIF(Bitácora!$F$5:$F$181,$B26),0) | I26: =COUNTIF(Impedimentos!$C$5:$C$64,$B26)
B27: Sprint 3 | C27: Recursos y recurrencia | D27: 46295 | E27: 46308 | F27: 9 | G27: =COUNTIFS(Bitácora!$F$5:$F$181,$B27,Bitácora!$P$5:$P$181,"Sí") | H27: =IFERROR($G27/COUNTIF(Bitácora!$F$5:$F$181,$B27),0) | I27: =COUNTIF(Impedimentos!$C$5:$C$64,$B27)
B28: Sprint 4 | C28: Trabajo planificado | D28: 46309 | E28: 46322 | F28: 10 | G28: =COUNTIFS(Bitácora!$F$5:$F$181,$B28,Bitácora!$P$5:$P$181,"Sí") | H28: =IFERROR($G28/COUNTIF(Bitácora!$F$5:$F$181,$B28),0) | I28: =COUNTIF(Impedimentos!$C$5:$C$64,$B28)
B29: Sprint 5 | C29: Ejecución | D29: 46323 | E29: 46336 | F29: 10 | G29: =COUNTIFS(Bitácora!$F$5:$F$181,$B29,Bitácora!$P$5:$P$181,"Sí") | H29: =IFERROR($G29/COUNTIF(Bitácora!$F$5:$F$181,$B29),0) | I29: =COUNTIF(Impedimentos!$C$5:$C$64,$B29)
B30: Sprint 6 | C30: Inteligencia y cierre | D30: 46337 | E30: 46350 | F30: 10 | G30: =COUNTIFS(Bitácora!$F$5:$F$181,$B30,Bitácora!$P$5:$P$181,"Sí") | H30: =IFERROR($G30/COUNTIF(Bitácora!$F$5:$F$181,$B30),0) | I30: =COUNTIF(Impedimentos!$C$5:$C$64,$B30)
B31: Total | F31: =SUM(F25:F30) | G31: =SUM(G25:G30) | H31: =IFERROR(G31/COUNTA(Bitácora!$A$5:$A$181),0) | I31: =SUM(I25:I30)
B33: Días sin Daily por feriado
B34: Fecha | C34: Feriado | D34: Sprint afectado
B35: 46283 | C35: Independencia Nacional | D35: Sprint 2
B36: 46307 | C36: Encuentro de Dos Mundos | D36: Sprint 3
B38: El 19 de septiembre y el 31 de octubre de 2026 caen sábado, y el 1 de noviembre domingo: no reducen días hábiles del Sprint.
B40: Por qué el registro va por delante del calendario
B41: Dejamos constancia de algo que se ve en las fechas: vamos adelantados respecto del calendario. SIGMA son 785 puntos, 138 historias y 20 épicas para un equipo de tres, y la única forma de absorber ese alcance fue adelantar construcción: lo que aquí se registra en la ventana del Sprint 4 y del Sprint 5 quedó construido y verificado contra la base entre el 11 y el 14 de septiembre. El registro mantiene el calendario planificado para no romper la trazabilidad con el Sprint Backlog, el burndown y los informes de prueba. Los Sprints 1 a 3 están cerrados y verificados con evidencia; del Sprint 4 se entregaron 9 de 24 historias y del Sprint 5, 8 de 26. El Sprint 6 no tiene registro diario todavía porque ninguna de sus historias está Terminada: se llenará cuando se ejecute.

Sheet Bitácora
A1: Bitácora de Daily Scrum
A2: Registro breve y periódico del avance, los impedimentos y los próximos pasos. Se completa en los quince minutos del Daily, no después.
A4: N.º | B4: Fecha | C4: Día | D4: Integrante | E4: Rol | F4: Sprint | G4: Sem. Sprint | H4: Sem. acad. | I4: Qué hice desde el último Daily | J4: Qué haré hasta el próximo Daily | K4: Impedimentos | L4: Historia | M4: Tarea | N4: Estado en GitHub Projects | O4: Issue / PR | P4: Realizado | Q4: Acuerdo del equipo y próximos pasos
A5: 0 | B5: 46264 | C5: domingo | D5: Bryan Chávez | E5: Developer | F5: Sprint 1 | G5: Previa | H5: S4 | I5: Construí la API REST de SIGMA sobre el proyecto Solucion/SIGMA/API: 14 controllers con los endpoints de las 17 historias del Sprint 1 (sesión, permisos, clientes, plantas, áreas, centros de costo, usuarios, perfiles, grupos, especialidades, permisos puntuales, catálogos, recuperación y mi perfil). Antes construí la base transversal: ErrorSql, que traduce cada RAISERROR de un SP a su código HTTP; ApiBase, con la validación y el 404; Datos, el mapeador a DTO que resuelve el NULL una sola vez; Pagina; CacheCorta; y el token JWT con el usuario y el cliente adentro. Compila en exitcode=0. | J5: Levantar la API en IIS y ejercitar los endpoints de punta a punta contra la base: hoy solo está verificado que compila. Empezar por POST /sesion, que es de donde salen los tokens del resto. | L5: HU-001, HU-002, HU-003, HU-006, HU-010 a HU-017, HU-020, HU-021 | M5: T-1006, T-1017, T-1030, T-1032, T-1046, T-1059, T-1061, T-1076, T-1078, T-1092, T-1094, T-1107, T-1120, T-1122, T-1136, T-1138, T-1152, T-1154, T-1168, T-1170, T-1183, T-1195, T-1197, T-1211, T-1213, T-1226, T-1228, T-1240 | N5: In Review | P5: Sí | Q5: Trabajo de PREPARACIÓN, anterior al inicio formal del Sprint 1 (02-09). Se registra con semana "Previa" para no falsear las fechas. Acuerdo: la API queda construida y compilando; probarla y documentarla es lo siguiente, y sin eso ninguna historia pasa de "En revisión".
A6: 0 | B6: 46264 | C6: domingo | D6: Emilio Fuentes | E6: Scrum Master | F6: Sprint 1 | G6: Previa | H6: S4 | I6: Definí con Bryan el manejo de errores de los SPs, que era la tarea que se repetía en cuatro historias: severidad 16 es una regla de negocio y el texto decide el código (409 si ya existe, 423 si está bloqueada, 403, 404, 400); cualquier otra cosa es 500 y su detalle NO viaja al cliente, queda en el log. También la caché corta de 60 segundos para permisos y catálogos, y los DTO de salida para que no se filtren hash, sal ni columnas de auditoría. | J6: Revisar con Catalina el orden de las pruebas del sprint, partiendo por HU-001 y HU-006, que son de las que dependen las demás. | K6: SMTP sigue sin configurar: HU-004 queda bloqueada. El token de recuperación se genera y se guarda, pero el correo no sale. | L6: HU-001, HU-002, HU-003, HU-004, HU-006, HU-011 a HU-017, HU-020, HU-021 | M6: T-1007, T-1018, T-1031, T-1033, T-1047, T-1060, T-1062, T-1077, T-1079, T-1093, T-1095, T-1108, T-1121, T-1123, T-1137, T-1139, T-1153, T-1155, T-1169, T-1171, T-1184, T-1196, T-1198, T-1212, T-1214, T-1227, T-1239 | N6: In Review | P6: Sí | Q6: Trabajo de PREPARACIÓN, anterior al inicio formal del Sprint 1 (02-09). Se registra con semana "Previa" para no falsear las fechas. Acuerdo: la API queda construida y compilando; probarla y documentarla es lo siguiente, y sin eso ninguna historia pasa de "En revisión".
A7: 0 | B7: 46264 | C7: domingo | D7: Catalina Pescio | E7: Product Owner | F7: Sprint 1 | G7: Previa | H7: S4 | I7: Revisé que los endpoints respondan a lo que piden las historias. Levanté una desviación en T-1226: la tarea pedía un alta idempotente por uuid para "mi perfil", pero mi perfil no se crea, se edita, así que no hay alta ni uuid que repetir. Se acordó entregar PUT /mi-perfil y POST /mi-perfil/password, que es lo que HU-005 realmente necesita, y dejar la desviación anotada en la tarea. | J7: Escribir y ejecutar un caso de prueba por cada criterio de aceptación de las 17 historias, y documentar los endpoints. Son las 34 tareas de Pruebas y Documentación del sprint, todas pendientes: nada de lo construido está probado todavía. | L7: Las 17 historias del Sprint 1 | M7: T-1011, T-1012 y las demás de Pruebas y Documentación | N7: Todo | P7: Sí | Q7: Trabajo de PREPARACIÓN, anterior al inicio formal del Sprint 1 (02-09). Se registra con semana "Previa" para no falsear las fechas. Acuerdo: la API queda construida y compilando; probarla y documentarla es lo siguiente, y sin eso ninguna historia pasa de "En revisión".
A8: 0 | B8: 46266 | C8: martes | D8: Bryan Chávez | E8: Developer | F8: Sprint 3 | G8: Previa | H8: S4 | I8: Me enfrenté a cinco frentes. Primero creé el módulo de INVENTARIO: el maestro de repuestos, la bodega y sus ubicaciones, el control de los movimientos con su trazabilidad completa, el saldo por ubicación, y le incorporé una carga masiva desde Excel para hacerle más ágil la carga de datos al bodeguero. Junto a Emilio incorporamos también el código automático, que quedó aplicado en ese módulo. Después incorporé las ALERTAS: detección continua, consulta, severidad según el quiebre de la alerta, el panel de la campana, y creé una bandeja de entrada para tener esa información a modo histórico. También completé el módulo de TERCEROS, que contempla la creación de proveedores y el permiso de trabajo con la vigencia de los trabajadores. De la mano de eso incorporé Azure Blob Storage para almacenar la documentación de los permisos de trabajo: hicimos ese ajuste para no guardarla directo en la base de datos. Y hoy avancé la PROGRAMACIÓN del mantenimiento: dejé la base —23 procedimientos, la función que proyecta las fechas y las dos pantallas, compilando— más el bloque de procedimientos que estaba escrito y sin aplicar. Al cierre arreglé el error que dejó master sin compilar. Todo esto está en el Excel del Sprint 3 como terminado en web y API; le faltan la documentación y las pruebas. | J8: Me quedo con las historias del módulo de programaciones: HU-070, HU-071, HU-072 y HU-075. Son cortas y van todas por lo mismo. Figuran como terminadas, pero las voy a revisar bien igual antes de darlas por cerradas. Voy a dejar la base de la programación sin ir más allá hasta que cerremos bien el otro sprint. Aparte abro el PR que desbloquea master, que hoy no compila, y saco del repositorio las carpetas de salida de compilación. | K8: Estoy un poco parado en programación: hay tareas que son del Sprint 4 que me tienen amarrado en el Sprint 3. No puedo generar ninguna ocurrencia del plan de mantenimiento, porque el plan es del Sprint 4 y nosotros estamos en el 3. Y tenía otro que dependía del Sprint 2: la historia HU-074, la del activo variable; esa tabla no tenía ningún registro, así que no pude hacer una prueba eficiente. Hay un tercero que quedó planteado y sin resolver: el medidor está amarrado a un solo horómetro y el criterio de HU-073 pide que cuatro equipos iguales disparen cada uno con el suyo. Los tres están en la hoja de Impedimentos, N.º 6 a 8. | L8: HU-050 a HU-060, HU-063, HU-064, HU-070 a HU-072, HU-075, HU-077 · toma HU-070, HU-071, HU-072 y HU-075 | M8: T-3201 a T-3205, T-3231 a T-3241, T-3042 a T-3052, T-3244 a T-3254, T-3016 a T-3027, T-3257 a T-3267, T-3113 a T-3126, T-3956, y las nuevas T-3960 a T-3971 | N8: In Review | O8: Rama fix/clases-duplicadas-activo · PR pendiente de abrir | P8: Sí | Q8: ACUERDO: las tareas quedan definidas en esta Daily. Emilio termina el Sprint 2 en web, base de datos y API —queda pendiente la app— y pasa a apoyar el Sprint 3 tomando HU-061 y HU-062, las dos de procedimientos, porque una depende de la otra. Bryan sigue con el módulo de programaciones: HU-070, HU-071, HU-072 y HU-075, dejando la base sin avanzar más hasta cerrar bien el sprint anterior. Catalina sigue con las pruebas: cierra el Sprint 1 con todo documentado, incluida la de la cuenta deshabilitada que ya puede crear, y de ahí pasa al Sprint 2. HU-151, trabajar sin conexión, QUEDA SIN ASIGNACIÓN: hay que analizarla antes, porque no está claro si se crea la tabla de sincronización o si va por SQLite en el teléfono; se acordó retomarla cuando se empiece con la aplicación móvil, ya que solo tiene tareas de base de datos, API y móvil. Se acordó también REVISAR lo que figura como terminado antes de darlo por cerrado, tanto en programaciones como en la base de datos de HU-061. NO SE RESOLVIERON las tres decisiones de modelo de los impedimentos N.º 6, 7 y 8, ni el estado de las cuatro historias construidas que siguen en "Por hacer" (HU-051, HU-060, HU-063, HU-064). Nota de calendario: es trabajo de PREPARACIÓN, por delante del inicio formal del Sprint 1 (02-09); se registra con semana "Previa", igual que el 30-08.
A9: 0 | B9: 46266 | C9: martes | D9: Emilio Fuentes | E9: Scrum Master | F9: Sprint 3 | G9: Previa | H9: S4 | I9: Logré completar nuevas historias. Arranqué con la HU-035, el registro de un activo: se puede dar de alta un equipo con su ficha técnica completa y el código se genera automático, para que no haya problema con las demás historias que también tienen que generarlo. Seguí con la HU-042, que configura el medidor de un activo —el horómetro o contador de horas—, con la idea de poder programar mantenimientos por uso y no solo por calendario. Después fui a los catálogos que describen el activo: la HU-030, tipo de activo, que quedó con un árbol de jerarquía de tipos y subtipos; la HU-031, modelos de activo, donde ya se distinguen los modelos globales de la plataforma de los propios de cada cliente, y me aseguré al dar de baja de que no queden datos colgados; y la HU-032, los atributos técnicos que definen qué datos describe cada tipo de activo, por ejemplo la potencia, el voltaje o el porcentaje. También cerré la HU-036, los componentes, que son las piezas que forman cada activo con su jerarquía de componente superior, y la HU-040, las unidades de medida: kilovatios, voltios, litros por minuto y varias más que se pueden ir agregando. Esas siete están construidas y compilan bien, y las dejé anotadas en revisión en el Excel, porque faltan las pruebas de navegación. Me quedan dos en curso, la HU-037 —ficha e historial de activos— y la HU-038 —cambio de estado de un activo con su motivo—: la parte web ya está terminada y falta solo el consumo desde la app. Todo quedó subido a mi rama, que ya está conversando con master. | J9: Del Sprint 2 estaría totalmente finalizado lo que es web, base de datos y API; queda pendiente la aplicación móvil y ya estaría listo para entregar al equipo de QA. Como Catalina va a seguir con las pruebas, yo paso a prestar apoyo en las tareas del Sprint 3: tomo la HU-061, administrar procedimientos reutilizables, y la HU-062, definir los pasos de un procedimiento, que dependen una de la otra. Cualquier duda le comunico a Bryan. Antes de avanzar voy a revisar qué está realmente creado, porque figura una parte como terminada y no está confirmado. | K9: Se ajustaron cosas de forma: el orden de los botones, el orden de los input, las palabras, y a la fecha se le agregó un calendario. El problema principal que tuve fue el de los códigos: al anotar un código uno podía poner cualquier número o letra, así que se automatizó y ahora se genera solo con las iniciales de cada módulo. Aparte, mi rama de HU-031 y la de Alertas/Terceros definieron las mismas clases y al mergear el PR #35 master dejó de compilar; ya está resuelto en una rama y falta mergear. | L9: En revisión: HU-030, HU-031, HU-032, HU-035, HU-036, HU-040, HU-042 · En curso: HU-037, HU-038 · toma HU-061 y HU-062 | N9: In Review | P9: Sí
A10: 0 | B10: 46266 | C10: martes | D10: Catalina Pescio | E10: Product Owner | F10: Sprint 3 | G10: Previa | H10: S4 | I10: Realicé la sincronización de mi branch, por el cambio de nombre. Ejecuté las pruebas de los diferentes casos según los criterios de aceptación que se habían previsto, y realicé también un informe de las pruebas que queda guardado como evidencia, en un archivo MD. Eso es del Sprint 1. Quedó pendiente el tercer criterio, porque no tenía una cuenta deshabilitada para realizar la prueba. También instalé Swagger en la carpeta de la API para poder hacer las pruebas; solo quedó pendiente verlo funcionando. | J10: Cerrar ya el Sprint 1, con todas las pruebas completas y documentadas, y ver los avances de mis tareas del Sprint 2. Me falta la prueba de la cuenta deshabilitada y ya me dijeron que la puedo crear. | K10: Solamente la del usuario: no tenía una cuenta deshabilitada para probar el tercer criterio de aceptación. Y un error en la instalación del Swagger, que me hizo tomar un poco más de tiempo; queda pendiente verlo funcionando. | L10: Las 17 historias del Sprint 1 · pasa a las pruebas del Sprint 2 | N10: In Review | P10: Sí
A11: 1 | B11: 46267 | C11: miércoles | D11: Bryan Chávez | E11: Developer | F11: Sprint 1 | G11: Semana 1 | H11: S5 | I11: Levanté la base SIGMA en el servidor y corrí los scripts del modelo de seguridad. Escribí SEL_USUARIO_LOGIN y la validación de la contraseña con hash. | J11: Cerrar POST /api/auth/login y que el token baje con los permisos del usuario adentro. | K11: Ninguno. | L11: HU-001, HU-006 | M11: T-1001, T-1004, T-1006, T-1008 a T-1010, T-1014, T-1017, T-1901, T-1903, T-1905 a T-1906 | N11: In Progress | P11: Sí
A12: 1 | B12: 46267 | C12: miércoles | D12: Catalina Pescio | E12: Product Owner | F12: Sprint 1 | G12: Semana 1 | H12: S5 | I12: Leí las 17 historias comprometidas y anoté los criterios de aceptación que están escritos de forma ambigua, sobre todo los de permisos. | J12: Escribir la matriz de casos de prueba de HU-001 y HU-006, un caso por criterio. | K12: Ninguno. | L12: HU-001, HU-006 | M12: T-1003, T-1011 a T-1013, T-1016, T-1022 a T-1023 | N12: Todo | P12: Sí
A13: 1 | B13: 46267 | C13: miércoles | D13: Emilio Fuentes | E13: Scrum Master | F13: Sprint 1 | G13: Semana 1 | H13: S5 | I13: Armé el tablero en GitHub Projects con las 17 historias del Sprint 1 y las columnas Todo, In Progress, In Review, Done y Blocked. Repasé con Bryan el patrón de páginas ASP. | J13: Construir Login.aspx contra el endpoint de Bryan y dejar el menú lateral leyendo desde Menus. | K13: Ninguno. | L13: HU-001, HU-006 | M13: T-1002, T-1005, T-1007, T-1015, T-1018 a T-1021, T-1902, T-1904 | N13: In Progress | P13: Sí | Q13: Se define el ritmo del Sprint: Daily a las 19:00 por Meet, quince minutos. Bryan toma el motor de datos y la API, Emilio las pantallas de seguridad y Catalina las pruebas y la documentación. Nada entra a master sin pull request.
A14: 2 | B14: 46268 | C14: jueves | D14: Bryan Chávez | E14: Developer | F14: Sprint 1 | G14: Semana 1 | H14: S5 | I14: Terminé el login: el endpoint entrega el token y Token.PuedeVer ya filtra el menú. Empecé los SP del maestro de usuarios. | J14: Dejar INS, UPD y DEL_USUARIO dentro de transacción, con la validación de correo duplicado. | K14: Ninguno. | L14: HU-001, HU-014 | M14: T-1001, T-1004, T-1006, T-1008 a T-1010, T-1024, T-1027, T-1030, T-1032, T-1034, T-1036 a T-1037, T-1906 | N14: In Review | O14: #12 | P14: Sí
A15: 2 | B15: 46268 | C15: jueves | D15: Catalina Pescio | E15: Product Owner | F15: Sprint 1 | G15: Semana 1 | H15: S5 | I15: Ejecuté los casos de HU-001. Encontré que la cuenta deshabilitada entraba igual: el SP no revisaba el estado. | J15: Reejecutar HU-001 con el arreglo y empezar los casos de HU-002. | K15: La base no tenía ninguna cuenta deshabilitada para probar el criterio 3; la creé yo. | L15: HU-001, HU-002 | M15: T-1003, T-1011 a T-1012, T-1043, T-1051 a T-1052 | N15: In Review | P15: Sí
A16: 2 | B16: 46268 | C16: jueves | D16: Emilio Fuentes | E16: Scrum Master | F16: Sprint 1 | G16: Semana 1 | H16: S5 | I16: Dejé andando Login.aspx y la selección de cliente cuando el usuario pertenece a más de uno: el combo aparece solo si hay más de una opción. | J16: Montar el listado Usuarios.aspx con la ficha en RadWindow. | K16: Ninguno. | L16: HU-002, HU-014 | M16: T-1025, T-1028, T-1031, T-1033, T-1035, T-1042, T-1045, T-1047 a T-1048, T-1050 | N16: In Progress | P16: Sí | Q16: Se acuerda que ninguna pantalla se da por terminada sin su fila en Menus: sin esa fila el permiso no existe y la página queda fuera del control de acceso.
A17: 3 | B17: 46269 | C17: viernes | D17: Bryan Chávez | E17: Developer | F17: Sprint 1 | G17: Semana 1 | H17: S5 | I17: Escribí los SP de perfiles y de la tabla puente Perfil_Menu, con la regla de que un perfil sin ningún permiso no se puede guardar. | J17: Exponer los endpoints de perfiles y armar el árbol de permisos desde el servidor. | K17: Ninguno. | L17: HU-015 | M17: T-1054, T-1057, T-1059, T-1061, T-1063, T-1065 a T-1066 | N17: In Progress | P17: Sí
A18: 3 | B18: 46269 | C18: viernes | D18: Catalina Pescio | E18: Product Owner | F18: Sprint 1 | G18: Semana 1 | H18: S5 | I18: Documenté en Swagger los endpoints de login y de usuarios, y dejé escritos los casos de HU-014. | J18: Probar HU-014 de punta a punta, incluida la validación de correo repetido. | K18: Ninguno. | L18: HU-014, HU-015 | M18: T-1026, T-1029, T-1038 a T-1040, T-1053, T-1056, T-1067 a T-1069 | N18: In Progress | P18: Sí
A19: 3 | B19: 46269 | C19: viernes | D19: Emilio Fuentes | E19: Scrum Master | F19: Sprint 1 | G19: Semana 1 | H19: S5 | I19: Armé la pantalla de perfiles con el árbol de menús y una casilla por permiso. | J19: Terminar el guardado del árbol y registrar Perfiles.aspx en Menus. | K19: El RadTreeView pierde las marcas en el postback; lo estoy resolviendo con ViewState. | L19: HU-015 | M19: T-1055, T-1058, T-1060, T-1062, T-1064 | N19: In Progress | P19: Sí | Q19: Perfiles y permisos queda como la historia más pesada del Sprint: se le dan dos días completos y nadie más toca esas tablas mientras tanto.
A20: 4 | B20: 46272 | C20: lunes | D20: Bryan Chávez | E20: Developer | F20: Sprint 1 | G20: Semana 1 | H20: S6 | I20: Cerré perfiles y pasé a la organización: SP de plantas y de áreas, con la jerarquía de área padre e hija. | J20: Dejar los endpoints de plantas y áreas, y el filtro de áreas por planta. | K20: Ninguno. | L20: HU-015, HU-011, HU-012 | M20: T-1054, T-1057, T-1059, T-1061, T-1063, T-1065 a T-1066, T-1071, T-1074, T-1076, T-1078, T-1081, T-1087, T-1090, T-1092, T-1094, T-1096, T-1098 a T-1099 | N20: In Review | O20: #18 | P20: Sí
A21: 4 | B21: 46272 | C21: lunes | D21: Catalina Pescio | E21: Product Owner | F21: Sprint 1 | G21: Semana 1 | H21: S6 | I21: Probé HU-015 completa: el perfil sin permisos ya no se guarda y el usuario ve solo lo que le corresponde. | J21: Escribir los casos de plantas y áreas, con foco en el borrado lógico de un área que tiene hijas. | K21: Ninguno. | L21: HU-015, HU-011, HU-012 | M21: T-1053, T-1056, T-1067 a T-1070, T-1073, T-1084 a T-1086, T-1089, T-1100 a T-1101 | N21: In Review | P21: Sí
A22: 4 | B22: 46272 | C22: lunes | D22: Emilio Fuentes | E22: Scrum Master | F22: Sprint 1 | G22: Semana 1 | H22: S6 | I22: Terminé el árbol de permisos y lo registré en Menus. Empecé Plantas.aspx con el mapa de Google. | J22: Terminar el mapa de la planta y montar Areas.aspx colgando de la planta seleccionada. | K22: No está confirmado que la clave de Google Maps tenga restricción de dominio. | L22: HU-015, HU-011 | M22: T-1055, T-1058, T-1060, T-1062, T-1064, T-1072, T-1075, T-1077, T-1079 a T-1080, T-1082 a T-1083 | N22: In Progress | P22: Sí
A23: 5 | B23: 46273 | C23: martes | D23: Bryan Chávez | E23: Developer | F23: Sprint 1 | G23: Semana 1 | H23: S6 | I23: Dejé listos los SP del cierre de sesión con expiración por inactividad y los del maestro de clientes. | J23: Terminar el endpoint de logout y revisar que todos los SEL filtren por cliente. | K23: Ninguno. | L23: HU-003, HU-010 | M23: T-1103, T-1106 a T-1107, T-1116, T-1119 a T-1120, T-1122, T-1124, T-1126 a T-1127 | N23: In Progress | P23: Sí
A24: 5 | B24: 46273 | C24: martes | D24: Catalina Pescio | E24: Product Owner | F24: Sprint 1 | G24: Semana 1 | H24: S6 | I24: Ejecuté los casos de plantas y áreas. El área con hijas se dejaba deshabilitar sin avisar; quedó reportado. | J24: Probar el cierre de sesión y la expiración por inactividad. | K24: Ninguno. | L24: HU-011, HU-012, HU-003 | M24: T-1070, T-1073, T-1084 a T-1086, T-1089, T-1100 a T-1102, T-1105, T-1112 a T-1113 | N24: In Review | P24: Sí
A25: 5 | B25: 46273 | C25: martes | D25: Emilio Fuentes | E25: Scrum Master | F25: Sprint 1 | G25: Semana 1 | H25: S6 | I25: Terminé plantas y áreas, las dos registradas en Menus con su permiso. Empecé Clientes.aspx. | J25: Cerrar la ficha del cliente y dejar la sesión expirando a los treinta minutos en el lado web. | K25: Ninguno. | L25: HU-011, HU-012, HU-010 | M25: T-1072, T-1075, T-1077, T-1079 a T-1080, T-1082 a T-1083, T-1088, T-1091, T-1093, T-1095, T-1097, T-1114, T-1117, T-1121, T-1123, T-1125 | N25: In Review | O25: #21 | P25: Sí | Q25: Se confirma que todo borrado del sistema es lógico: se marca deshabilitado y se rechaza con mensaje si el registro está en uso.
A26: 6 | B26: 46274 | C26: miércoles | D26: Bryan Chávez | E26: Developer | F26: Sprint 1 | G26: Semana 2 | H26: S6 | I26: Escribí los SP de especialidades y certificaciones del usuario, y el del permiso puntual con su fecha de vigencia. | J26: Dejar el endpoint del permiso puntual y que Token.Puede lo sume al permiso del perfil. | K26: Ninguno. | L26: HU-017, HU-007 | M26: T-1132, T-1135 a T-1136, T-1138, T-1141, T-1148, T-1151 a T-1152, T-1154, T-1156, T-1158 a T-1159 | N26: In Progress | P26: Sí
A27: 6 | B27: 46274 | C27: miércoles | D27: Catalina Pescio | E27: Product Owner | F27: Sprint 1 | G27: Semana 2 | H27: S6 | I27: Documenté clientes, plantas y áreas en Swagger y actualicé el MD de estado. | J27: Escribir los casos de HU-007: que el permiso puntual sume y que caduque solo. | K27: Ninguno. | L27: HU-010, HU-011, HU-007 | M27: T-1070, T-1073, T-1084 a T-1085, T-1115, T-1118, T-1128 a T-1129, T-1147, T-1150, T-1160 a T-1161 | N27: In Progress | P27: Sí
A28: 6 | B28: 46274 | C28: miércoles | D28: Emilio Fuentes | E28: Scrum Master | F28: Sprint 1 | G28: Semana 2 | H28: S6 | I28: Cerré clientes. Monté la pestaña de especialidades dentro de la ficha del usuario. | J28: Armar la pantalla del permiso puntual y probar que convive con el permiso del perfil. | K28: Ninguno. | L28: HU-010, HU-017 | M28: T-1114, T-1117, T-1121, T-1123, T-1125, T-1130, T-1133, T-1137, T-1139 a T-1140, T-1142 a T-1143 | N28: In Progress | P28: Sí
A29: 7 | B29: 46275 | C29: jueves | D29: Bryan Chávez | E29: Developer | F29: Sprint 1 | G29: Semana 2 | H29: S6 | I29: Terminé el permiso puntual: Token.Puede ya suma perfil más excepción. Dejé el SP de grupos de trabajo. | J29: Escribir el flujo de recuperación de contraseña con token de un solo uso, aunque todavía no se pueda enviar el correo. | K29: El servidor SMTP no está configurado: HU-004 no se puede probar de punta a punta. | L29: HU-007, HU-016, HU-004 | M29: T-1148, T-1151 a T-1152, T-1154, T-1156, T-1158 a T-1159, T-1164, T-1167 a T-1168, T-1170, T-1173, T-1180, T-1183, T-1185 a T-1186, T-1907 | N29: Blocked | P29: Sí
A30: 7 | B30: 46275 | C30: jueves | D30: Catalina Pescio | E30: Product Owner | F30: Sprint 1 | G30: Semana 2 | H30: S6 | I30: Probé HU-007 y HU-017. El permiso puntual vencido seguía dando acceso hasta el siguiente login; quedó reportado. | J30: Dejar escritos los casos de HU-004 para ejecutarlos cuando haya correo. | K30: HU-004 no se puede ejecutar sin SMTP. | L30: HU-007, HU-017, HU-004 | M30: T-1131, T-1134, T-1144 a T-1145, T-1147, T-1150, T-1160 a T-1161, T-1179, T-1182, T-1187 a T-1188 | N30: Blocked | P30: Sí
A31: 7 | B31: 46275 | C31: jueves | D31: Emilio Fuentes | E31: Scrum Master | F31: Sprint 1 | G31: Semana 2 | H31: S6 | I31: Monté la pantalla de grupos de trabajo con la asignación de integrantes. | J31: Cerrar grupos y ayudar con la pantalla de recuperación de contraseña. | K31: Sigo sin los datos del servidor de correo para configurar Web.config. | L31: HU-016, HU-004 | M31: T-1162, T-1165, T-1169, T-1171 a T-1172, T-1174 a T-1175, T-1178, T-1181, T-1184 | N31: In Progress | P31: Sí | Q31: HU-004 queda BLOQUEADA por SMTP y no cuenta para el compromiso del Sprint. Se registra el impedimento y se sigue con el resto.
A32: 8 | B32: 46276 | C32: viernes | D32: Bryan Chávez | E32: Developer | F32: Sprint 1 | G32: Semana 2 | H32: S6 | I32: Dejé el motor de catálogos ampliables: el valor propio del cliente convive con el valor de sistema y no lo pisa. | J32: Terminar los SP de centros de costo y el endpoint del catálogo consolidado. | K32: Ninguno. | L32: HU-021, HU-013 | M32: T-1189, T-1192, T-1195, T-1197, T-1200, T-1205, T-1208, T-1211, T-1213, T-1215, T-1217 a T-1218 | N32: In Progress | P32: Sí
A33: 8 | B33: 46276 | C33: viernes | D33: Catalina Pescio | E33: Product Owner | F33: Sprint 1 | G33: Semana 2 | H33: S6 | I33: Ejecuté HU-016 y empecé los casos del catálogo ampliable. | J33: Probar que un cliente no vea los valores propios de otro cliente. | K33: Ninguno. | L33: HU-016, HU-021 | M33: T-1163, T-1166, T-1176 a T-1177, T-1191, T-1194, T-1203 a T-1204 | N33: In Progress | P33: Sí
A34: 8 | B34: 46276 | C34: viernes | D34: Emilio Fuentes | E34: Scrum Master | F34: Sprint 1 | G34: Semana 2 | H34: S6 | I34: Terminé grupos de trabajo y armé la pantalla del catálogo ampliable, distinguiendo en la grilla el valor de sistema del propio. | J34: Montar centros de costo y registrar las dos pantallas en Menus. | K34: Ninguno. | L34: HU-016, HU-021, HU-013 | M34: T-1162, T-1165, T-1169, T-1171 a T-1172, T-1174 a T-1175, T-1190, T-1193, T-1196, T-1198 a T-1199, T-1201 a T-1202, T-1206, T-1209, T-1212, T-1214, T-1216 | N34: In Progress | P34: Sí
A35: 9 | B35: 46279 | C35: lunes | D35: Bryan Chávez | E35: Developer | F35: Sprint 1 | G35: Semana 2 | H35: S7 | I35: Cerré centros de costo y el perfil propio con cambio de contraseña. La contraseña antigua se valida en el servidor, no en la pantalla. | J35: Revisar los pull request abiertos y dejar master compilando. | K35: Ninguno. | L35: HU-013, HU-005, HU-020 | M35: T-1205, T-1208, T-1211, T-1213, T-1215, T-1217 a T-1218, T-1221, T-1224, T-1226, T-1228, T-1230 a T-1231, T-1236, T-1240, T-1242 | N35: In Review | O35: #27 | P35: Sí
A36: 9 | B36: 46279 | C36: lunes | D36: Catalina Pescio | E36: Product Owner | F36: Sprint 1 | G36: Semana 2 | H36: S7 | I36: Probé el catálogo ampliable y el cambio de contraseña. Los valores propios no se cruzan entre clientes. | J36: Cerrar la ejecución de las 17 historias y dejar el informe de pruebas del Sprint 1. | K36: Ninguno. | L36: HU-021, HU-005, HU-020 | M36: T-1191, T-1194, T-1203 a T-1204, T-1223, T-1233 a T-1235, T-1238, T-1243 a T-1244 | N36: In Review | P36: Sí
A37: 9 | B37: 46279 | C37: lunes | D37: Emilio Fuentes | E37: Scrum Master | F37: Sprint 1 | G37: Semana 2 | H37: S7 | I37: Terminé la consulta de catálogos del sistema y la pantalla de Mi perfil. | J37: Revisar los PR de Bryan y cerrar el tablero para la revisión del Sprint. | K37: Ninguno. | L37: HU-020, HU-005 | M37: T-1222, T-1225, T-1227, T-1229, T-1232, T-1237, T-1239, T-1241 | N37: In Review | P37: Sí | Q37: Mañana se congela el desarrollo: solo corrección de lo que devuelvan las pruebas y cierre de la Definition of Done.
A38: 10 | B38: 46280 | C38: martes | D38: Bryan Chávez | E38: Developer | F38: Sprint 1 | G38: Semana 2 | H38: S7 | I38: Mergeé los pull request pendientes y dejé master compilando. Corregí lo que devolvieron las pruebas de permisos. | J38: Preparar el modelo de activos para el Sprint 2. | K38: Ninguno. | L38: HU-001, HU-002, HU-003, HU-005, HU-006, HU-007 | M38: T-1001, T-1004, T-1006, T-1008 a T-1010, T-1014, T-1017, T-1041, T-1044, T-1046, T-1049, T-1103, T-1106 a T-1107, T-1148, T-1151 a T-1152, T-1154, T-1156, T-1158 a T-1159, T-1221, T-1224, T-1226, T-1228, T-1230 a T-1231, T-1901, T-1903, T-1905 a T-1906 | N38: Done | O38: #31 | P38: Sí
A39: 10 | B39: 46280 | C39: martes | D39: Catalina Pescio | E39: Product Owner | F39: Sprint 1 | G39: Semana 2 | H39: S7 | I39: Recorrí en navegador las 16 historias terminadas y las acepté una por una contra sus criterios. | J39: Escribir por adelantado los casos de prueba de las historias de activos. | K39: Ninguno. | L39: HU-014, HU-017, HU-020, HU-021 | M39: T-1026, T-1029, T-1038 a T-1040, T-1131, T-1134, T-1144 a T-1145, T-1191, T-1194, T-1203 a T-1204, T-1235, T-1238, T-1243 a T-1244 | N39: Done | P39: Sí
A40: 10 | B40: 46280 | C40: martes | D40: Emilio Fuentes | E40: Scrum Master | F40: Sprint 1 | G40: Semana 2 | H40: S7 | I40: Facilité la revisión del Sprint con la Product Owner y moví a Done lo aceptado. Actualicé el burndown. | J40: Armar el tablero del Sprint 2 con las 22 historias de activos y suscripciones. | K40: Ninguno. | L40: HU-010, HU-011, HU-012, HU-013, HU-015, HU-016 | M40: T-1055, T-1058, T-1060, T-1062, T-1064, T-1072, T-1075, T-1077, T-1079 a T-1080, T-1082 a T-1083, T-1088, T-1091, T-1093, T-1095, T-1097, T-1114, T-1117, T-1121, T-1123, T-1125, T-1162, T-1165, T-1169, T-1171 a T-1172, T-1174 a T-1175, T-1206, T-1209, T-1212, T-1214, T-1216 | N40: Done | P40: Sí | Q40: Sprint 1 cerrado: 16 de 17 historias terminadas. HU-004 queda bloqueada por SMTP y se arrastra. En la retrospectiva se acuerda escribir los casos de prueba antes de programar, no después.
A41: 11 | B41: 46281 | C41: miércoles | D41: Bryan Chávez | E41: Developer | F41: Sprint 2 | G41: Semana 1 | H41: S7 | I41: Corrí los scripts del modelo de activos y dejé los SP de tipos de activo con el código automático por iniciales. | J41: Dejar los SP de modelos de activo y su relación con la marca. | K41: Ninguno. | L41: HU-030, HU-031 | N41: In Progress | P41: Sí
A42: 11 | B42: 46281 | C42: miércoles | D42: Catalina Pescio | E42: Product Owner | F42: Sprint 2 | G42: Semana 1 | H42: S7 | I42: Traje escritos los casos de tipos y modelos de activo, como quedamos en la retro. | J42: Ejecutar los casos de HU-030 en cuanto Emilio deje la pantalla. | K42: Ninguno. | L42: HU-030, HU-031 | M42: T-2235 a T-2236, T-2277 a T-2278 | N42: Todo | P42: Sí
A43: 11 | B43: 46281 | C43: miércoles | D43: Emilio Fuentes | E43: Scrum Master | F43: Sprint 2 | G43: Semana 1 | H43: S7 | I43: Monté TiposActivo.aspx con su ficha y la registré en Menus. Retomé HU-004 apenas quedó el correo configurado. | J43: Montar Modelos.aspx y dejar el filtro de modelos por familia. | K43: Ninguno. | L43: HU-030, HU-031, HU-004 | M43: T-2221 a T-2226, T-2231 a T-2234, T-2263 a T-2268, T-2273 a T-2276 | N43: In Progress | P43: Sí | Q43: Se parte por los maestros: sin tipos ni modelos de activo no se puede registrar un activo. Emilio toma el grueso de las pantallas web de este Sprint.
A44: 12 | B44: 46282 | C44: jueves | D44: Bryan Chávez | E44: Developer | F44: Sprint 2 | G44: Semana 1 | H44: S7 | I44: Dejé el motor de atributos técnicos: cada tipo de activo define sus propios campos y la unidad con la que se miden. | J44: Escribir los SP de posición funcional con la jerarquía planta, área y posición. | K44: Ninguno. | L44: HU-032, HU-033 | M44: T-2089, T-2092, T-2099, T-2101 | N44: In Progress | P44: Sí
A45: 12 | B45: 46282 | C45: jueves | D45: Catalina Pescio | E45: Product Owner | F45: Sprint 2 | G45: Semana 1 | H45: S7 | I45: Probé tipos y modelos. El código automático repetía el correlativo cuando dos usuarios grababan a la vez; quedó reportado. | J45: Escribir y ejecutar los casos de atributos técnicos. | K45: Ninguno. | L45: HU-030, HU-031, HU-032 | M45: T-2235 a T-2236, T-2277 a T-2278, T-2309 a T-2310 | N45: In Review | P45: Sí
A46: 12 | B46: 46282 | C46: jueves | D46: Emilio Fuentes | E46: Scrum Master | F46: Sprint 2 | G46: Semana 1 | H46: S7 | I46: Terminé modelos de activo y armé la pantalla de atributos técnicos por tipo. | J46: Montar Posiciones.aspx con el árbol de la planta. | K46: Ninguno. | L46: HU-031, HU-032, HU-033 | M46: T-2090, T-2093, T-2098, T-2100, T-2263 a T-2268, T-2273 a T-2276, T-2295 a T-2300, T-2305 a T-2308 | N46: In Progress | P46: Sí
A47: 13 | B47: 46286 | C47: lunes | D47: Bryan Chávez | E47: Developer | F47: Sprint 2 | G47: Semana 1 | H47: S8 | I47: Corregí el correlativo del código automático usando ROWCOUNT dentro de la transacción. Dejé el SP que genera el contenido del QR de la posición. | J47: Dejar los SP del alta de activo: serie, modelo, posición y estado inicial. | K47: Ninguno. | L47: HU-034, HU-035 | M47: T-2173, T-2179 | N47: In Progress | P47: Sí
A48: 13 | B48: 46286 | C48: lunes | D48: Catalina Pescio | E48: Product Owner | F48: Sprint 2 | G48: Semana 1 | H48: S8 | I48: Ejecuté los casos de posición funcional y del QR. El QR impreso apunta a la posición correcta. | J48: Escribir los casos del alta de activo, que tiene siete criterios. | K48: Ninguno. | L48: HU-033, HU-034, HU-035 | M48: T-2015 a T-2017, T-2088, T-2091, T-2102 a T-2103, T-2172, T-2175, T-2180 a T-2181 | N48: In Review | P48: Sí
A49: 13 | B49: 46286 | C49: lunes | D49: Emilio Fuentes | E49: Scrum Master | F49: Sprint 2 | G49: Semana 1 | H49: S8 | I49: Terminé posiciones funcionales y monté la pantalla de impresión del QR, con la hoja de etiquetas. | J49: Armar Activos.aspx, que es la ficha más grande del Sprint. | K49: Ninguno. | L49: HU-033, HU-034, HU-035 | M49: T-2001 a T-2006, T-2011 a T-2014, T-2090, T-2093, T-2098, T-2100, T-2171, T-2174, T-2178 | N49: In Progress | P49: Sí | Q49: El QR de la posición se resuelve en el servidor y no en la pantalla, así el mismo código sirve para la web y para la app.
A50: 14 | B50: 46287 | C50: martes | D50: Bryan Chávez | E50: Developer | F50: Sprint 2 | G50: Semana 1 | H50: S8 | I50: Cerré el alta de activo y empecé los componentes: un activo puede tener hijos y el hijo hereda la posición del padre. | J50: Dejar el SP de la ficha consolidada del activo con su historial. | K50: Ninguno. | L50: HU-035, HU-036, HU-037 | N50: In Progress | P50: Sí
A51: 14 | B51: 46287 | C51: martes | D51: Catalina Pescio | E51: Product Owner | F51: Sprint 2 | G51: Semana 1 | H51: S8 | I51: Probé el alta de activo. La serie duplicada se dejaba grabar dentro del mismo cliente; quedó reportado. | J51: Reejecutar HU-035 con el arreglo y probar componentes. | K51: Ninguno. | L51: HU-035, HU-036 | M51: T-2015 a T-2017, T-2118 a T-2119 | N51: In Review | P51: Sí
A52: 14 | B52: 46287 | C52: martes | D52: Emilio Fuentes | E52: Scrum Master | F52: Sprint 2 | G52: Semana 1 | H52: S8 | I52: Terminé la ficha del activo con sus pestañas y dejé la grilla de componentes dentro de la misma ficha. | J52: Montar la pestaña de historial del activo y registrar las pestañas nuevas en Menus. | K52: Ninguno. | L52: HU-035, HU-036, HU-037 | M52: T-2001 a T-2006, T-2011 a T-2014, T-2049 a T-2057, T-2104 a T-2109, T-2114 a T-2117 | N52: In Review | O52: #44 | P52: Sí
A53: 15 | B53: 46288 | C53: miércoles | D53: Bryan Chávez | E53: Developer | F53: Sprint 2 | G53: Semana 2 | H53: S8 | I53: Dejé el cambio de estado del activo con motivo obligatorio y la bitácora del cambio. Empecé unidades de medida. | J53: Terminar los SP de unidades y de variables de condición. | K53: Ninguno. | L53: HU-038, HU-040, HU-041 | M53: T-2154, T-2237, T-2240, T-2248 | N53: In Progress | P53: Sí
A54: 15 | B54: 46288 | C54: miércoles | D54: Catalina Pescio | E54: Product Owner | F54: Sprint 2 | G54: Semana 2 | H54: S8 | I54: Probé componentes y el historial de la ficha. Documenté en Swagger los endpoints de activos. | J54: Ejecutar los casos del cambio de estado y de unidades. | K54: Ninguno. | L54: HU-036, HU-037, HU-038 | M54: T-2058 a T-2059, T-2118 a T-2119, T-2156 a T-2157 | N54: In Review | P54: Sí
A55: 15 | B55: 46288 | C55: miércoles | D55: Emilio Fuentes | E55: Scrum Master | F55: Sprint 2 | G55: Semana 2 | H55: S8 | I55: Monté la pantalla de cambio de estado y las de unidades de medida y variables de condición. | J55: Cerrar variables de condición y dejar las tres pantallas registradas en Menus. | K55: Ninguno. | L55: HU-038, HU-040, HU-041 | M55: T-2146 a T-2153, T-2155, T-2238, T-2241, T-2247, T-2249 a T-2250, T-2279 a T-2284, T-2289 a T-2292 | N55: In Progress | P55: Sí | Q55: Se acuerda que el cambio de estado del activo siempre exige motivo: sin motivo el servidor rechaza, aunque la pantalla lo permita.
A56: 16 | B56: 46289 | C56: jueves | D56: Bryan Chávez | E56: Developer | F56: Sprint 2 | G56: Semana 2 | H56: S8 | I56: Dejé el medidor del activo con su lectura inicial y la regla de que la lectura nueva no puede ser menor que la anterior salvo reemplazo del medidor. | J56: Escribir los endpoints de lectura de medidor y de medición de condición para la app. | K56: Ninguno. | L56: HU-042, HU-043, HU-044 | M56: T-2061, T-2064, T-2066, T-2070 a T-2071, T-2121, T-2124, T-2126, T-2130 a T-2131 | N56: In Progress | P56: Sí
A57: 16 | B57: 46289 | C57: jueves | D57: Catalina Pescio | E57: Product Owner | F57: Sprint 2 | G57: Semana 2 | H57: S8 | I57: Ejecuté el cambio de estado y unidades. El motivo vacío pasaba por la API aunque la pantalla lo exigía; quedó reportado. | J57: Escribir los casos de lectura de medidor y de medición de condición. | K57: Ninguno. | L57: HU-038, HU-040, HU-042 | M57: T-2032 a T-2033, T-2156 a T-2157, T-2293 a T-2294 | N57: In Review | P57: Sí
A58: 16 | B58: 46289 | C58: jueves | D58: Emilio Fuentes | E58: Scrum Master | F58: Sprint 2 | G58: Semana 2 | H58: S8 | I58: Terminé variables de condición y monté la configuración del medidor dentro de la ficha del activo. | J58: Apoyar la parte móvil de la lectura de medidor. | K58: Ninguno. | L58: HU-041, HU-042 | M58: T-2018 a T-2023, T-2028 a T-2031, T-2238, T-2241, T-2247, T-2249 a T-2250 | N58: In Review | O58: #51 | P58: Sí
A59: 17 | B59: 46290 | C59: viernes | D59: Bryan Chávez | E59: Developer | F59: Sprint 2 | G59: Semana 2 | H59: S8 | I59: Dejé andando la serie histórica de una variable y arranqué la sincronización hacia el dispositivo: el paquete baja acotado al usuario y a su planta. | J59: Cerrar el endpoint de sync con marca de tiempo para que el teléfono pida solo lo cambiado. | K59: Ninguno. | L59: HU-045, HU-150 | M59: T-2034, T-2037 a T-2038, T-2040, T-2042, T-2044 a T-2045, T-2182, T-2185, T-2188 | N59: In Progress | P59: Sí
A60: 17 | B60: 46290 | C60: viernes | D60: Catalina Pescio | E60: Product Owner | F60: Sprint 2 | G60: Semana 2 | H60: S8 | I60: Probé el medidor y la medición de condición desde la app. Documenté los endpoints de la app en Swagger. | J60: Escribir los casos de la sincronización, que son los más largos del Sprint. | K60: Ninguno. | L60: HU-042, HU-043, HU-044 | M60: T-2032 a T-2033, T-2060, T-2063, T-2072 a T-2073, T-2120, T-2123, T-2132 a T-2133 | N60: In Review | P60: Sí
A61: 17 | B61: 46290 | C61: viernes | D61: Emilio Fuentes | E61: Scrum Master | F61: Sprint 2 | G61: Semana 2 | H61: S8 | I61: Monté la pantalla de la serie histórica con el gráfico y el filtro por rango de fechas. | J61: Empezar las pantallas del módulo comercial: planes y contratación. | K61: Ninguno. | L61: HU-045, HU-190, HU-191 | M61: T-2183, T-2189 | N61: In Progress | P61: Sí | Q61: La sincronización hacia el dispositivo es la historia de trece puntos del Sprint: se le da prioridad por sobre el módulo comercial.
A62: 18 | B62: 46293 | C62: lunes | D62: Bryan Chávez | E62: Developer | F62: Sprint 2 | G62: Semana 2 | H62: S9 | I62: Cerré la sincronización y dejé el escaneo del QR de la posición resolviendo contra la base local del teléfono. | J62: Dejar los SP del módulo de suscripciones: planes, contratación y vigencia. | K62: Ninguno. | L62: HU-150, HU-154, HU-190 | M62: T-2034, T-2037 a T-2038, T-2040, T-2042, T-2044 a T-2045, T-2076, T-2078, T-2080, T-2083, T-2192 a T-2197, T-2202 a T-2205 | N62: In Review | O62: #58 | P62: Sí
A63: 18 | B63: 46293 | C63: lunes | D63: Catalina Pescio | E63: Product Owner | F63: Sprint 2 | G63: Semana 2 | H63: S9 | I63: Ejecuté los casos de sincronización y del escaneo del QR. El teléfono resolvió el código sin señal. | J63: Probar el módulo comercial completo. | K63: Ninguno. | L63: HU-150, HU-154 | M63: T-2036, T-2046 a T-2048, T-2075, T-2086 a T-2087 | N63: In Review | P63: Sí
A64: 18 | B64: 46293 | C64: lunes | D64: Emilio Fuentes | E64: Scrum Master | F64: Sprint 2 | G64: Semana 2 | H64: S9 | I64: Terminé la administración de planes comerciales y la pantalla de contratación y renovación. | J64: Montar la consulta del estado de mi suscripción y el registro del pago. | K64: Ninguno. | L64: HU-190, HU-191, HU-192 | M64: T-2254 | N64: In Progress | P64: Sí
A65: 19 | B65: 46294 | C65: martes | D65: Bryan Chávez | E65: Developer | F65: Sprint 2 | G65: Semana 2 | H65: S9 | I65: Dejé el bloqueo por suscripción vencida operando en el servidor: la API responde 402 y la app muestra el aviso. | J65: Preparar el modelo de repuestos y de programaciones para el Sprint 3. | K65: Ninguno. | L65: HU-193, HU-194 | M65: T-2134 a T-2141, T-2143, T-2208 a T-2212, T-2216 a T-2218 | N65: Done | O65: #63 | P65: Sí
A66: 19 | B66: 46294 | C66: martes | D66: Catalina Pescio | E66: Product Owner | F66: Sprint 2 | G66: Semana 2 | H66: S9 | I66: Recorrí las 22 historias con el equipo y las acepté. El bloqueo por vencimiento deja pasar el login pero no la operación, como pide el criterio. | J66: Escribir por adelantado los casos del módulo de repuestos. | K66: Ninguno. | L66: HU-190, HU-191, HU-192, HU-193, HU-194 | M66: T-2144 a T-2145, T-2169 a T-2170, T-2206 a T-2207, T-2219 a T-2220, T-2255, T-2261 a T-2262 | N66: Done | P66: Sí
A67: 19 | B67: 46294 | C67: martes | D67: Emilio Fuentes | E67: Scrum Master | F67: Sprint 2 | G67: Semana 2 | H67: S9 | I67: Cerré el estado de la suscripción y el registro del pago. Facilité la revisión del Sprint y actualicé el burndown. | J67: Armar el tablero del Sprint 3 con las 29 historias de inventario y programación. | K67: Ninguno. | L67: HU-192, HU-193, HU-194 | M67: T-2142, T-2254 | N67: Done | P67: Sí | Q67: Sprint 2 cerrado: las 22 historias aceptadas, incluida HU-004 que venía arrastrada. Se detecta que la carga quedó cargada a Emilio en la parte web; se anota para revisarlo en la planificación siguiente.
A68: 20 | B68: 46295 | C68: miércoles | D68: Bryan Chávez | E68: Developer | F68: Sprint 3 | G68: Semana 1 | H68: S9 | I68: Corrí el modelo de inventario y dejé los SP del maestro de repuestos, la compatibilidad con modelos y el árbol de bodegas y ubicaciones. | J68: Montar las tres pantallas del maestro y registrarlas en Menus. | K68: Ninguno. | L68: HU-050, HU-051, HU-052 | M68: T-3086 a T-3091, T-3096 a T-3099, T-3159 a T-3164, T-3169 a T-3172, T-3175 a T-3180, T-3185 a T-3188 | N68: In Progress | P68: Sí
A69: 20 | B69: 46295 | C69: miércoles | D69: Catalina Pescio | E69: Product Owner | F69: Sprint 3 | G69: Semana 1 | H69: S9 | I69: Traje los casos del maestro de repuestos escritos desde el cierre del Sprint 2. | J69: Ejecutar los casos de HU-050 apenas esté la pantalla. | K69: Ninguno. | L69: HU-050, HU-051 | M69: T-3100 a T-3101, T-3173 a T-3174 | N69: Todo | P69: Sí
A70: 20 | B70: 46295 | C70: miércoles | D70: Emilio Fuentes | E70: Scrum Master | F70: Sprint 3 | G70: Semana 1 | H70: S9 | I70: Revisé el alcance de las 29 historias y armé el tablero. Tomé la parte de bodegas. | J70: Terminar Bodegas.aspx con el árbol de ubicaciones. | K70: Estoy con carga de otro ramo esta semana y voy a avanzar menos de lo que quisiera. | L70: HU-052 | N70: In Progress | P70: Sí | Q70: Sprint largo: 29 historias. Se arranca por el maestro de repuestos porque de él cuelga todo el resto del inventario.
A71: 21 | B71: 46296 | C71: jueves | D71: Bryan Chávez | E71: Developer | F71: Sprint 3 | G71: Semana 1 | H71: S9 | I71: Cerré el maestro de repuestos y la compatibilidad. Dejé el stock mínimo y máximo por bodega y el ingreso a bodega con su movimiento. | J71: Dejar la entrega de repuestos contra una orden de trabajo, con el descuento de stock dentro de la transacción. | K71: Ninguno. | L71: HU-050, HU-051, HU-053, HU-054 | M71: T-3056 a T-3061, T-3066 a T-3069, T-3086 a T-3091, T-3096 a T-3099, T-3129 a T-3138, T-3140, T-3159 a T-3164, T-3169 a T-3172 | N71: In Progress | P71: Sí
A72: 21 | B72: 46296 | C72: jueves | D72: Catalina Pescio | E72: Product Owner | F72: Sprint 3 | G72: Semana 1 | H72: S9 | I72: Probé el maestro de repuestos y la compatibilidad. El repuesto sin unidad de medida se dejaba grabar; quedó reportado. | J72: Escribir y ejecutar los casos de stock mínimo y de ingreso a bodega. | K72: Ninguno. | L72: HU-050, HU-051, HU-053 | M72: T-3070 a T-3071, T-3100 a T-3101, T-3173 a T-3174 | N72: In Review | P72: Sí
A73: 21 | B73: 46296 | C73: jueves | D73: Emilio Fuentes | E73: Scrum Master | F73: Sprint 3 | G73: Semana 1 | H73: S9 | I73: Terminé el árbol de bodegas y ubicaciones y lo registré en Menus. | J73: Apoyar la pantalla de ingreso a bodega. | K73: Ninguno. | L73: HU-052, HU-054 | M73: T-3139 | N73: In Review | O73: #71 | P73: Sí
A74: 22 | B74: 46297 | C74: viernes | D74: Bryan Chávez | E74: Developer | F74: Sprint 3 | G74: Semana 1 | H74: S9 | I74: Dejé la entrega contra orden de trabajo, la consulta de existencia y el ajuste de inventario con motivo obligatorio. | J74: Escribir la vida útil real del repuesto instalado, que necesita cruzar entrega con desinstalación. | K74: Ninguno. | L74: HU-055, HU-056, HU-057, HU-058 | M74: T-3072 a T-3081, T-3083, T-3102 a T-3110, T-3191 a T-3194, T-3197 a T-3198, T-3270 a T-3280 | N74: In Progress | P74: Sí
A75: 22 | B75: 46297 | C75: viernes | D75: Catalina Pescio | E75: Product Owner | F75: Sprint 3 | G75: Semana 1 | H75: S9 | I75: Ejecuté stock mínimo, ingreso a bodega y entrega contra orden. El stock quedaba negativo si se entregaba más de lo que había; quedó reportado. | J75: Reejecutar la entrega con el arreglo y probar el ajuste de inventario. | K75: Ninguno. | L75: HU-053, HU-054, HU-055 | M75: T-3070 a T-3071, T-3084 a T-3085, T-3141 a T-3142 | N75: In Review | P75: Sí
A76: 22 | B76: 46297 | C76: viernes | D76: Emilio Fuentes | E76: Scrum Master | F76: Sprint 3 | G76: Semana 1 | H76: S9 | I76: Monté la consulta de existencia, que es la pantalla que más van a usar en terreno. | J76: Terminar la consulta y dejarla también respondiendo por la API para la app. | K76: Ninguno. | L76: HU-056 | N76: In Progress | P76: Sí | Q76: Se acuerda que ningún movimiento de inventario se graba fuera de transacción: si falla el detalle, no queda el encabezado.
A77: 23 | B77: 46300 | C77: lunes | D77: Bryan Chávez | E77: Developer | F77: Sprint 3 | G77: Semana 1 | H77: S10 | I77: Cerré la vida útil del repuesto instalado y dejé la trazabilidad por estante y lote, que era la historia de ocho puntos del inventario. Empecé las etiquetas QR de bodega. | J77: Dejar la consulta por escaneo de etiqueta resolviendo bodega, ubicación y repuesto con el mismo lector. | K77: Ninguno. | L77: HU-058, HU-059, HU-066 | M77: T-3191 a T-3194, T-3197 a T-3198, T-3910 a T-3917, T-3920 a T-3926 | N77: In Progress | P77: Sí
A78: 23 | B78: 46300 | C78: lunes | D78: Catalina Pescio | E78: Product Owner | F78: Sprint 3 | G78: Semana 1 | H78: S10 | I78: Probé el ajuste de inventario y la vida útil. Documenté en Swagger todo el módulo de inventario. | J78: Escribir los casos de la trazabilidad por estante y lote. | K78: Ninguno. | L78: HU-057, HU-058 | M78: T-3199 a T-3200, T-3281 a T-3282 | N78: In Review | P78: Sí
A79: 23 | B79: 46300 | C79: lunes | D79: Emilio Fuentes | E79: Scrum Master | F79: Sprint 3 | G79: Semana 1 | H79: S10 | I79: Terminé la consulta de existencia y la dejé respondiendo por la API. | J79: Montar la pantalla de impresión de etiquetas QR. | K79: Ninguno. | L79: HU-056, HU-066 | N79: In Review | O79: #78 | P79: Sí
A80: 24 | B80: 46301 | C80: martes | D80: Bryan Chávez | E80: Developer | F80: Sprint 3 | G80: Semana 1 | H80: S10 | I80: Dejé la consulta por escaneo, la carga y descarga del maestro en planilla y la generación automática de códigos con las iniciales del tipo. | J80: Empezar el módulo de proveedores y procedimientos. | K80: Ninguno. | L80: HU-067, HU-068, HU-069 | M80: T-3929 a T-3933, T-3936 a T-3940, T-3942 a T-3944 | N80: In Progress | P80: Sí
A81: 24 | B81: 46301 | C81: martes | D81: Catalina Pescio | E81: Product Owner | F81: Sprint 3 | G81: Semana 1 | H81: S10 | I81: Ejecuté la trazabilidad por estante y lote y la carga en planilla. La planilla con una columna de más no avisaba y cargaba igual; quedó reportado. | J81: Probar la generación automática de códigos y el escaneo de etiquetas. | K81: Ninguno. | L81: HU-059, HU-066, HU-068 | M81: T-3918 a T-3919, T-3927 a T-3928, T-3941 | N81: In Review | P81: Sí
A82: 24 | B82: 46301 | C82: martes | D82: Emilio Fuentes | E82: Scrum Master | F82: Sprint 3 | G82: Semana 1 | H82: S10 | I82: Monté la pantalla de proveedores con su ficha. | J82: Sacar las carpetas de compilación del repositorio y terminar proveedores. | K82: La salida de compilación versionada ensucia todos los diff y hace ilegibles los pull request. | L82: HU-060 | N82: In Progress | P82: Sí | Q82: Se detecta que la salida de compilación de ASP.NET está versionada en el repositorio. Se registra el impedimento y Emilio la saca del control de versiones.
A83: 25 | B83: 46302 | C83: miércoles | D83: Bryan Chávez | E83: Developer | F83: Sprint 3 | G83: Semana 2 | H83: S10 | I83: Dejé los procedimientos reutilizables con sus pasos ordenados y el permiso de trabajo con su evidencia adjunta. | J83: Terminar los avisos del sistema, que es la historia que cruza todo el módulo. | K83: No existe todavía la API de almacenamiento de archivos, así que la evidencia del permiso queda con el formulario escondido y un aviso en pantalla. | L83: HU-061, HU-062, HU-063 | M83: T-3217 a T-3228, T-3970 | N83: In Progress | P83: Sí
A84: 25 | B84: 46302 | C84: miércoles | D84: Catalina Pescio | E84: Product Owner | F84: Sprint 3 | G84: Semana 2 | H84: S10 | I84: Probé el escaneo de etiquetas y los códigos automáticos. Empecé los casos de procedimientos. | J84: Ejecutar procedimientos y pasos, y documentarlos en Swagger. | K84: Ninguno. | L84: HU-067, HU-069, HU-061 | M84: T-3215 a T-3216, T-3935, T-3945 | N84: In Review | P84: Sí
A85: 25 | B85: 46302 | C85: miércoles | D85: Emilio Fuentes | E85: Scrum Master | F85: Sprint 3 | G85: Semana 2 | H85: S10 | I85: Terminé proveedores y limpié el repositorio: se sacaron las carpetas de compilación con git rm --cached. | J85: Montar la pantalla de pasos del procedimiento. | K85: Ninguno. | L85: HU-060, HU-062 | M85: T-3283 a T-3288, T-3293 a T-3296 | N85: In Review | O85: #84 | P85: Sí
A86: 26 | B86: 46303 | C86: jueves | D86: Bryan Chávez | E86: Developer | F86: Sprint 3 | G86: Semana 2 | H86: S10 | I86: Cerré permisos de trabajo, la consulta de permisos por vencer y el historial de servicios del proveedor. Arranqué las programaciones: fecha única y calendario. | J86: Dejar la programación por intervalo y la programación por medidor. | K86: Ninguno. | L86: HU-063, HU-064, HU-065, HU-070, HU-071 | M86: T-3042 a T-3046, T-3050 a T-3052, T-3217 a T-3228, T-3231 a T-3235, T-3239 a T-3241, T-3299 a T-3302, T-3305 a T-3306, T-3309 a T-3316, T-3902, T-3960 a T-3961, T-3964 a T-3965, T-3967 a T-3969 | N86: In Progress | P86: Sí
A87: 26 | B87: 46303 | C87: jueves | D87: Catalina Pescio | E87: Product Owner | F87: Sprint 3 | G87: Semana 2 | H87: S10 | I87: Ejecuté procedimientos, pasos y permisos de trabajo. El permiso vencido seguía apareciendo como vigente en la consulta; quedó reportado. | J87: Escribir los casos de las cinco formas de programación. | K87: Ninguno. | L87: HU-061, HU-062, HU-063, HU-064 | M87: T-3215 a T-3216, T-3229 a T-3230, T-3297 a T-3298, T-3317 a T-3318 | N87: In Review | P87: Sí
A88: 26 | B88: 46303 | C88: jueves | D88: Emilio Fuentes | E88: Scrum Master | F88: Sprint 3 | G88: Semana 2 | H88: S10 | I88: Terminé los pasos del procedimiento y ordené el reordenamiento por arrastre. | J88: Apoyar las pantallas de programación de calendario. | K88: Ninguno. | L88: HU-062, HU-071 | M88: T-3283 a T-3288, T-3293 a T-3296 | N88: In Review | O88: #88 | P88: Sí | Q88: Se acuerda que la generación de ocurrencias del Sprint 3 se deja calculando fechas aunque no exista todavía el plan de mantenimiento: el plan llega en el Sprint 4.
A89: 27 | B89: 46304 | C89: viernes | D89: Bryan Chávez | E89: Developer | F89: Sprint 3 | G89: Semana 2 | H89: S10 | I89: Dejé la programación por intervalo, la programación por medidor y las tolerancias y exclusiones. La programación por condición quedó a medias. | J89: Cerrar la programación por condición y el generador automático de ocurrencias. | K89: Programacion_Medidor.pme_activo_medidor es NOT NULL y no deja expresar «el medidor que tenga el activo». Además no existe tabla de feriados y SIGMA es multipaís. | L89: HU-072, HU-073, HU-074, HU-075 | M89: T-3017 a T-3020, T-3024 a T-3025, T-3115, T-3118, T-3124, T-3126, T-3244 a T-3248, T-3252 a T-3254, T-3257 a T-3261, T-3265 a T-3267, T-3962 a T-3963, T-3966, T-3971 | N89: In Progress | P89: Sí
A90: 27 | B90: 46304 | C90: viernes | D90: Catalina Pescio | E90: Product Owner | F90: Sprint 3 | G90: Semana 2 | H90: S10 | I90: Ejecuté los casos de las programaciones de fecha única, calendario e intervalo. Documenté el módulo en Swagger. | J90: Probar la programación por medidor y las tolerancias. | K90: Ninguno. | L90: HU-070, HU-071, HU-072 | M90: T-3053 a T-3055, T-3242 a T-3243, T-3255 a T-3256 | N90: In Review | P90: Sí
A91: 27 | B91: 46304 | C91: viernes | D91: Emilio Fuentes | E91: Scrum Master | F91: Sprint 3 | G91: Semana 2 | H91: S10 | I91: Terminé las pantallas de calendario y ayudé a revisar los pull request acumulados. | J91: Revisar los PR abiertos y dejar master compilando antes del cierre. | K91: Estoy avanzando menos que Bryan y se nota en el tablero. | L91: HU-070, HU-071 | N91: In Review | P91: Sí | Q91: La carga de este Sprint quedó muy desbalanceada: Bryan tomó la mayor parte de las historias de programación. Se acuerda repartir de otra forma en el Sprint 4.
A92: 28 | B92: 46308 | C92: martes | D92: Bryan Chávez | E92: Developer | F92: Sprint 3 | G92: Semana 2 | H92: S11 | I92: Cerré el generador de ocurrencias con el cálculo de fechas y los avisos del sistema. Dejé master compilando después de arreglar las clases duplicadas del PR #35. | J92: Preparar el reparto del Sprint 4 con Emilio y Catalina. | K92: HU-076 no genera ninguna ocurrencia real: falta el plan de mantenimiento, que es del Sprint 4. | L92: HU-076, HU-077 | M92: T-3030 a T-3038, T-3946 a T-3957 | N92: Done | O92: #35 | P92: Sí
A93: 28 | B93: 46308 | C93: martes | D93: Catalina Pescio | E93: Product Owner | F93: Sprint 3 | G93: Semana 2 | H93: S11 | I93: Recorrí las historias terminadas y las acepté. Dejé el informe de pruebas del Sprint 3 y planteé en la retro que quiero tomar tareas de desarrollo, no solo de pruebas. | J93: Preparar con el equipo el reparto del Sprint 4 tomando historias web y de API. | K93: HU-151 no se puede probar: quedó sin asignación. | L93: HU-073, HU-074, HU-075, HU-151 | M93: T-3003, T-3013 a T-3015, T-3027 a T-3029, T-3114, T-3117, T-3127 a T-3128, T-3268 a T-3269 | N93: Done | P93: Sí
A94: 28 | B94: 46308 | C94: martes | D94: Emilio Fuentes | E94: Scrum Master | F94: Sprint 3 | G94: Semana 2 | H94: S11 | I94: Facilité la revisión del Sprint y la retrospectiva. Actualicé el burndown y moví a Done lo aceptado. | J94: Armar el tablero del Sprint 4 y preparar la planificación con el reparto nuevo. | K94: Ninguno. | L94: HU-070, HU-071, HU-060, HU-062 | M94: T-3283 a T-3288, T-3293 a T-3296 | N94: Done | P94: Sí | Q94: Sprint 3 cerrado. HU-151 queda sin asignación porque depende del paquete de sincronización completo y HU-076 no puede generar ocurrencias hasta que exista el plan de mantenimiento del Sprint 4. En la retrospectiva se acuerda cambiar la forma de repartir: por historia completa y no por tipo de tarea.
A95: 29 | B95: 46309 | C95: miércoles | D95: Bryan Chávez | E95: Developer | F95: Sprint 4 | G95: Semana 1 | H95: S11 | I95: Repartimos las 274 tareas del Sprint 4 con el criterio nuevo. Quedé con HU-080, HU-081, HU-083, HU-085, HU-095, HU-096, HU-102 y HU-104: 91 tareas y 58 horas, incluido todo el checklist en terreno, que es la historia de trece puntos. | J95: Arrancar por HU-080 completa: modelo de Plan_Mantenimiento, los cinco SP, el listado y la ficha, y el permiso en el servidor. Recién cuando esté cerrada paso a HU-081. | K95: HU-095 depende de HU-094, que también es de este Sprint: hay que coordinar el orden con Emilio. | L95: HU-080, HU-081, HU-083, HU-085, HU-095, HU-096, HU-102, HU-104 | M95: T-4001 a T-4006, T-4011 a T-4014, T-4018 a T-4023, T-4028 a T-4031, T-4035 a T-4041, T-4043 a T-4046, T-4084 a T-4087, T-4090 a T-4091, T-4094 a T-4099, T-4104 a T-4107, T-4212 a T-4215, T-4218 a T-4219, T-4283 a T-4287, T-4291 a T-4293, T-4322 a T-4333 | N95: In Progress | P95: Sí
A96: 29 | B96: 46309 | C96: miércoles | D96: Catalina Pescio | E96: Product Owner | F96: Sprint 4 | G96: Semana 1 | H96: S11 | I96: Tomé por primera vez historias de desarrollo: HU-082, HU-087, HU-091, HU-092, HU-097, HU-101, HU-140 y HU-141, 93 tareas y 58 horas, con 14 tareas web y 6 de API. HU-140 y HU-141 son mías de punta a punta, endpoints incluidos. | J96: Empezar HU-101, crear una tarea, que es la más simple de las mías, para tomar el ritmo del patrón de páginas antes de meterme en las de API. | K96: Nunca he escrito un endpoint del proyecto: voy a necesitar que Bryan me muestre el patrón de la API y el middleware de la KEY. | L96: HU-082, HU-087, HU-091, HU-092, HU-097, HU-101, HU-140, HU-141 | M96: T-4050 a T-4055, T-4060 a T-4063, T-4121 a T-4126, T-4131 a T-4134, T-4138 a T-4144, T-4146 a T-4149, T-4178 a T-4181, T-4184 a T-4185, T-4222 a T-4228, T-4230 a T-4233, T-4251 a T-4256, T-4261 a T-4264, T-4267 a T-4272, T-4277 a T-4280, T-4296 a T-4299, T-4302 a T-4303 | N96: In Progress | P96: Sí
A97: 29 | B97: 46309 | C97: miércoles | D97: Emilio Fuentes | E97: Scrum Master | F97: Sprint 4 | G97: Semana 1 | H97: S11 | I97: Facilité la planificación y dejé el tablero del Sprint 4 con las 24 historias y los tres responsables. Quedé con HU-084, HU-086, HU-090, HU-093, HU-094, HU-100, HU-103 y HU-160: 90 tareas y 58 horas. | J97: Partir por HU-090, la plantilla de checklist, que es la más pesada de las mías y de la que dependen HU-091 y HU-093. | K97: Ninguno. | L97: HU-084, HU-086, HU-090, HU-093, HU-094, HU-100, HU-103, HU-160 | M97: T-4067 a T-4072, T-4077 a T-4080, T-4110 a T-4114, T-4117 a T-4118, T-4152 a T-4158, T-4160 a T-4163, T-4167 a T-4171, T-4174 a T-4175, T-4188 a T-4192, T-4195 a T-4196, T-4199 a T-4203, T-4207 a T-4209, T-4237 a T-4243, T-4245 a T-4248, T-4306 a T-4311, T-4316 a T-4319 | N97: In Progress | P97: Sí | Q97: ACUERDO DEL REPARTO DEL SPRINT 4. Se cambia la forma de repartir: la unidad de reparto pasa a ser la historia completa y no el tipo de tarea. Cada historia tiene un dueño único que hace todo su desarrollo (modelo, SP, endpoint, pantalla, registro en Menus y permiso con Token.Puede); nadie más toca esa tabla ni esos archivos, con lo que se terminan los conflictos de merge que arrastramos desde el Sprint 3. El bloque de verificación de cada historia (Pruebas, Documentación y Validación) siempre queda en manos de alguien distinto del dueño. Catalina deja de ser solo pruebas y toma ocho historias de desarrollo, con trabajo web y de API. El reparto queda en 8 historias propias y 8 de verificación por persona, 58,0 horas exactas cada uno sobre las 174 del Sprint. Se registra en la hoja Tareas y en la columna Responsable de la hoja Historias del Sprint Backlog S4.
A98: 30 | B98: 46310 | C98: jueves | D98: Bryan Chávez | E98: Developer | F98: Sprint 4 | G98: Semana 1 | H98: S11 | I98: Levanté HU-080 de punta a punta por la base: modelo de Plan_Mantenimiento con su versión, y los SP SEL/INS/UPD/DEL siguiendo PATRONES/ASP —código único por cliente, FNC_PAIS_HORA para la fecha y baja lógica—. Un plan nace siempre en borrador: publicarlo es otra historia y no quise mezclarlas. | J98: Cerrar HU-080 con el listado, la ficha y el permiso en el servidor, y dejarla registrada en Menus. | K98: Ninguno. | L98: HU-080 | M98: T-4001 a T-4006 | N98: In Progress | P98: Sí
A99: 30 | B99: 46310 | C99: jueves | D99: Catalina Pescio | E99: Product Owner | F99: Sprint 4 | G99: Semana 1 | H99: S11 | I99: Revisé el patrón de la API con Bryan: controlador, Datos.Listar, ExigirPermiso y el middleware de la KEY. Dejé anotado el esqueleto que voy a seguir en mis endpoints. | J99: Partir HU-101, crear una tarea, que es la más simple de las mías. | K99: Sigo sin haber escrito un endpoint del proyecto; la sesión de traspaso ayudó pero necesito hacer uno completo para tomar el patrón. | L99: HU-101 | M99: T-4251 a T-4253 | N99: Todo | P99: Sí
A100: 30 | B100: 46310 | C100: jueves | D100: Emilio Fuentes | E100: Scrum Master | F100: Sprint 4 | G100: Semana 1 | H100: S11 | I100: Empecé HU-090, la plantilla de checklist, que es la más pesada de las mías: el modelo de Checklist_Plantilla con su versión y los primeros SP siguiendo PATRONES/ASP. | J100: Seguir con los ítems de la plantilla y su orden dentro de la sección. | K100: Ninguno. | L100: HU-090 | M100: T-4067 a T-4069 | N100: In Progress | P100: Sí
A101: 31 | B101: 46311 | C101: viernes | D101: Bryan Chávez | E101: Developer | F101: Sprint 4 | G101: Semana 1 | H101: S11 | I101: Cerré HU-080: listado con búsqueda y filtro, ficha en modal con las clases sigma-modal-*, permiso validado en el servidor con Token.Puede y las dos pantallas registradas en Menus. Un plan sin planta ya no se guarda. | J101: Arrancar HU-081, los hitos del plan, que solo se pueden tocar sobre una versión en borrador. | K101: Ninguno. | L101: HU-080 | M101: T-4007 a T-4014 | N101: In Review | P101: Sí | Q101: Dejamos constancia de algo que se ve en las fechas: vamos adelantados respecto del calendario. SIGMA son 785 puntos, 138 historias y 20 épicas para un equipo de tres, y la única forma de absorber ese alcance fue adelantar construcción: lo que aquí se registra en la ventana del Sprint 4 y del Sprint 5 quedó construido y verificado contra la base entre el 11 y el 14 de septiembre. El registro mantiene el calendario planificado para no romper la trazabilidad con el Sprint Backlog, el burndown y los informes de prueba.
...

Sheet Impedimentos
A1: Registro de impedimentos
A2: Todo impedimento declarado en un Daily se anota aquí el mismo día. El Scrum Master es responsable de su gestión y de su cierre.
A4: N.º | B4: Fecha de detección | C4: Sprint | D4: Detectado por | E4: Descripción del impedimento | F4: Tipo | G4: Historia / Tarea afectada | H4: Responsable de resolver | I4: Acción tomada | J4: Estado | K4: Fecha de resolución | L4: Días abierto
A5: 1 | B5: 46264 | C5: Sprint 1 | D5: Bryan Chávez | E5: El servidor SMTP no está configurado. Web.config apunta a smtp.pendiente-de-configurar.cl, así que HU-004 emite el token de recuperación pero el correo nunca sale. Es lo único que impide cerrar una historia del Sprint 1 por causa ajena al código. | F5: Acceso o infraestructura | G5: HU-004 · Recuperar mi contraseña | H5: Emilio Fuentes | I5: Reprogramado al Sprint 6 en la Sprint Review 1 (15-09-2026): toda la infraestructura y los servicios externos se concentran ahí y los provee Código Creativo (T-6301). HU-004 queda construida y en revisión; el criterio del correo se verifica en el Sprint 6. | J5: En gestión | L5: =IF($B5="","",IF($J5="Resuelto",IF($K5="","",$K5-$B5),TODAY()-$B5))
A6: 2 | B6: 46264 | C6: Sprint 1 | D6: Bryan Chávez | E6: No existe la API de almacenamiento de archivos (Blob). Web.config tiene AlmacenamientoApiUrl = PENDIENTE. Hoy impide declarar un pago —el comprobante es obligatorio— y en el Sprint 2 bloquea las evidencias fotográficas, que son ruta crítica. | F6: Dependencia externa | G6: Sprint 2 · Evidencias y archivos | H6: Bryan Chávez | I6: Reprogramado al Sprint 6 en la Sprint Review 1 (15-09-2026), junto con las evidencias desde terreno (HU-140/141): Código Creativo decide proveedor y levanta el servicio (T-6302). Las pantallas web siguen avisando y escondiendo el formulario mientras tanto. | J6: En gestión | L6: =IF($B6="","",IF($J6="Resuelto",IF($K6="","",$K6-$B6),TODAY()-$B6))
A7: 3 | B7: 46264 | C7: Sprint 1 | D7: Bryan Chávez | E7: El proyecto no está en un repositorio git. Sin historial no hay diff que revisar, así que el criterio 9 de la Definition of Done —revisión de código por otro integrante— no se puede cumplir por definición. También obliga a mover a _RETIRADO/ lo que se da de baja, en vez de borrarlo. | F7: Equipo | G7: Definition of Done · criterio 9 | H7: Emilio Fuentes | I7: Pendiente: crear el repositorio y subir el estado actual. Mientras tanto, lo retirado se conserva en C:\Capstone\_RETIRADO con su motivo. | J7: Abierto | L7: =IF($B7="","",IF($J7="Resuelto",IF($K7="","",$K7-$B7),TODAY()-$B7))
A8: 4 | B8: 46264 | C8: Sprint 1 | D8: Bryan Chávez | E8: No está confirmado que la clave de Google Maps tenga restricción por referrer HTTP. Esa clave es pública por diseño —viaja en el script de la página— y lo único que la protege es la restricción en la consola de Google. Sin ella, quien la copie factura contra nuestra cuenta. | F8: Acceso o infraestructura | G8: HU-011 · Administrar las plantas del cliente | H8: Bryan Chávez | I8: Reprogramado al Sprint 6 en la Sprint Review 1 (15-09-2026): restricción de la clave en la consola de Google Cloud (T-6303). | J8: En gestión | L8: =IF($B8="","",IF($J8="Resuelto",IF($K8="","",$K8-$B8),TODAY()-$B8))
A9: 5 | B9: 46264 | C9: Sprint 1 | D9: Bryan Chávez | E9: Ninguna de las 17 historias se ha recorrido en navegador. No es formalidad: el 30-08, abriendo dos pantallas, aparecieron cuatro fallas que el compilador no detecta (dbo.SPLIT inexistente, contraseñas en texto plano, una FK violada al cambiar de perfil y una tabla ausente). | F9: Equipo | G9: Sprint 1 · las 17 historias | H9: Catalina Pescio | I9: Pendiente: sesión de recorrido con la Product Owner. Es lo que separa "En revisión" de "Terminada". | J9: Abierto | L9: =IF($B9="","",IF($J9="Resuelto",IF($K9="","",$K9-$B9),TODAY()-$B9))
A10: 6 | B10: 46266 | C10: Sprint 3 | D10: Bryan Chávez | E10: HU-076 no puede generar ninguna ocurrencia. Plan_Mantenimiento_Ocurrencia.pmo_plan_mantenimiento_hito es NOT NULL contra Plan_Mantenimiento_Hito, que la crea HU-081 del Sprint 4 y hoy tiene cero filas. Los 21 criterios de las siete historias de programación dicen "entonces se genera la ocurrencia", así que ninguno se puede demostrar de punta a punta. | F10: Alcance o requisito | G10: HU-076 · Generar las ocurrencias de forma automática | H10: Catalina Pescio | I10: Mitigado: el cálculo de fechas —lo difícil— ya está hecho y probado en FNC_PROGRAMACION_FECHAS, y el generador lo reutiliza tal cual. Falta decidir si se adelanta una rebanada de datos del Sprint 4 (unas 6 h de SPs, sin pantallas) o si HU-076 se mueve entera al Sprint 4. | J10: Abierto | L10: =IF($B10="","",IF($J10="Resuelto",IF($K10="","",$K10-$B10),TODAY()-$B10))
A11: 7 | B11: 46266 | C11: Sprint 3 | D11: Bryan Chávez | E11: HU-074 está bloqueada por una historia del Sprint 2. Programacion_Condicion apunta a Activo_Variable, que tiene cero filas y ningún mantenedor: eso es HU-041 "Administrar variables de condición", que sigue en Por hacer. El CRUD de condiciones quedó terminado, pero el combo de la ficha aparece sin opciones. | F11: Dependencia externa | G11: HU-074 · Crear una programación por condición · depende de HU-041 | H11: Catalina Pescio | I11: Se dejó SEL_ACTIVO_VARIABLE mínimo para que la pantalla pueda armarse y avisa "no hay variables definidas todavía" en vez de mostrar un desplegable vacío. Falta decidir si HU-041 se trae al Sprint 3 o si HU-074 se saca. | J11: Abierto | L11: =IF($B11="","",IF($J11="Resuelto",IF($K11="","",$K11-$B11),TODAY()-$B11))
A12: 8 | B12: 46266 | C12: Sprint 3 | D12: Bryan Chávez | E12: Programacion_Medidor.pme_activo_medidor es NOT NULL, así que la regla "cada 500 horas" está obligada a nombrar UN horómetro concreto. El criterio 3 de HU-073 pide lo contrario: un plan sobre cuatro blowers idénticos donde cada equipo dispara con su propio horómetro y sin crear cuatro programaciones. | F12: Técnico | G12: HU-073 · Crear una programación por medidor, criterio 3 | H12: Bryan Chávez | I12: La columna debería ser nullable, con NULL = "el medidor que traiga cada activo del plan", que sale de Plan_Mantenimiento_Activo.pac_activo_medidor. Es un ALTER aditivo, pero cambia el modelo y lo decide el equipo. No se aplicó por cuenta propia. | J12: Abierto | L12: =IF($B12="","",IF($J12="Resuelto",IF($K12="","",$K12-$B12),TODAY()-$B12))
A13: 9 | B13: 46266 | C13: Sprint 3 | D13: Bryan Chávez | E13: No existe tabla de feriados y SIGMA es multipaís. El criterio 2 de HU-075 habla de "excluyo los feriados" como si fuera un calendario nacional. | F13: Alcance o requisito | G13: HU-075 · Definir tolerancias y exclusiones, criterio 2 | H13: Catalina Pescio | I13: Hoy se resuelve cargando cada feriado a mano como exclusión con desplazamiento, que funciona y ya está probado, pero obliga a cargarlos cliente por cliente y año por año. Falta decidir si se modela una tabla de feriados por país. | J13: Abierto | L13: =IF($B13="","",IF($J13="Resuelto",IF($K13="","",$K13-$B13),TODAY()-$B13))
A14: 10 | B14: 46266 | C14: Sprint 3 | D14: Bryan Chávez | E14: La salida de compilación de ASP.NET está versionada en el repositorio: tres carpetas "_program files_git_check" con DLLs y archivos .compiled, en la raíz, en Web/Intranet y en App_Code. Cada compilación las modifica —una verificación de hoy ensució 190 archivos— así que van a chocar en cada merge entre ramas. | F14: Equipo | G14: Definition of Done · repositorio limpio | H14: Emilio Fuentes | I14: Pendiente: sacarlas del control de versiones con git rm --cached y agregarlas al .gitignore. No se metió en el PR del día para no mezclarlo con el arreglo de compilación. | J14: Abierto | L14: =IF($B14="","",IF($J14="Resuelto",IF($K14="","",$K14-$B14),TODAY()-$B14))
A15: 11 | B15: 46266 | C15: Sprint 3 | D15: Bryan Chávez | E15: master quedó sin compilar. Al mergear el PR #35 quedaron cuatro clases definidas dos veces —ActivoModelo, ActivoComponente y sus dos controladores— entre ActivoAlcance.cs y los archivos por entidad. El error visible era CS0101, pero el compilador se detiene en la primera y en realidad eran cuatro. | F15: Técnico | G15: Sprint 3 · rama master | H15: Bryan Chávez | I15: Resuelto: se eliminaron los ActivoAlcance*, que eran subconjunto y además leían una columna ETIQUETA que SEL_ACTIVO_COMPONENTE no devuelve. La única propiedad que solo existía ahí —ActivoComponente.etiqueta, que usa RepuestoCompatibilidad.aspx.cs— se movió calculada al archivo por entidad. Rama fix/clases-duplicadas-activo, compilando en EXITCODE=0. Falta abrir y mergear el PR. | J15: En gestión | L15: =IF($B15="","",IF($J15="Resuelto",IF($K15="","",$K15-$B15),TODAY()-$B15))
A16: 12 | B16: 46031 | C16: Sprint 3 | D16: Catalina Pescio | E16: No había una cuenta deshabilitada en la base para poder ejecutar el tercer criterio de aceptación de HU-001. La prueba quedó sin correr. | F16: Acceso o infraestructura | G16: HU-001 · Iniciar sesión, criterio 3 | H16: Catalina Pescio | I16: Resuelto: se confirmó que Catalina puede crear la cuenta deshabilitada ella misma. Queda ejecutar la prueba. | J16: Resuelto | K16: 46031 | L16: =IF($B16="","",IF($J16="Resuelto",IF($K16="","",$K16-$B16),TODAY()-$B16))
A17: 13 | B17: 46031 | C17: Sprint 3 | D17: Catalina Pescio | E17: Error en la instalación de Swagger en la carpeta de la API, que tomó más tiempo del previsto. Quedó instalado pero todavía no se ha visto funcionando. | F17: Técnico | G17: Pruebas del Sprint 1 · documentación de la API | H17: Catalina Pescio | I17: Pendiente: verificar que Swagger levante y responda antes de cerrar la documentación de los endpoints. | J17: Abierto | L17: =IF($B17="","",IF($J17="Resuelto",IF($K17="","",$K17-$B17),TODAY()-$B17))
A18: 14 | B18: 46031 | C18: Sprint 3 | D18: Bryan Chávez | E18: HU-151, trabajar sin conexión, no se puede asignar todavía: no está definido si se resuelve creando la tabla de sincronización en el servidor o con SQLite en el teléfono. Sus tareas son solo de base de datos, API y móvil; no tiene parte web. | F18: Alcance o requisito | G18: HU-151 · Trabajar sin conexión | H18: Bryan Chávez | I18: Acordado en el Daily: queda SIN ASIGNACIÓN y se retoma cuando se empiece a trabajar la aplicación móvil. Antes hay que analizar la historia entre los tres. | J18: Abierto | L18: =IF($B18="","",IF($J18="Resuelto",IF($K18="","",$K18-$B18),TODAY()-$B18))
A19: 15 | B19: 46031 | C19: Sprint 3 | D19: Emilio Fuentes | E19: Los códigos se podían anotar a mano con cualquier número o letra, así que dos personas nombraban distinto el mismo registro. | F19: Técnico | G19: Módulo de activos e inventario · códigos | H19: Emilio Fuentes | I19: Resuelto: se automatizó la generación del código con las iniciales de cada módulo, y quedó aplicado también en inventario. | J19: Resuelto | K19: 46031 | L19: =IF($B19="","",IF($J19="Resuelto",IF($K19="","",$K19-$B19),TODAY()-$B19))
A20: 16 | B20: 46295 | C20: Sprint 3 | D20: Emilio Fuentes | E20: Emilio declara carga académica de otro ramo durante la semana 1 del Sprint 3. La capacidad real del equipo baja y la parte web se concentra en Bryan. | F20: Equipo | G20: Sprint 3 — módulo de inventario | H20: Emilio Fuentes | I20: Mitigado: Bryan absorbe las historias de programación. Se acuerda revisar el reparto en la planificación del Sprint 4. | J20: Resuelto | K20: 46309 | L20: =IF($B20="","",IF($J20="Resuelto",IF($K20="","",$K20-$B20),TODAY()-$B20))
A21: 17 | B21: 46309 | C21: Sprint 4 | D21: Bryan Chávez | E21: HU-095 depende de HU-094 y las dos son del mismo Sprint. Si la programación del checklist no está publicada, la ejecución en terreno no tiene qué bajar al teléfono. | F21: Dependencia externa | G21: HU-095 — Ejecutar un checklist en terreno | H21: Emilio Fuentes | I21: Acordado en el Daily: Emilio adelanta HU-094 en los primeros días para desbloquear a Bryan. | J21: En gestión | L21: =IF($B21="","",IF($J21="Resuelto",IF($K21="","",$K21-$B21),TODAY()-$B21))
A22: 18 | B22: 46309 | C22: Sprint 4 | D22: Catalina Pescio | E22: Catalina toma por primera vez tareas de API y no conoce el patrón de los controladores ni el middleware que valida la KEY del cliente contra FNC_SUSCRIPCION. | F22: Equipo | G22: HU-140 y HU-141 — tareas de API | H22: Bryan Chávez | I22: Acordado en el Daily: Bryan hace una sesión de traspaso del patrón de la API antes de que Catalina empiece HU-140. | J22: En gestión | L22: =IF($B22="","",IF($J22="Resuelto",IF($K22="","",$K22-$B22),TODAY()-$B22))
A23: 19 | B23: 46322 | C23: Sprint 4 | D23: Bryan Chávez | E23: HU-082 (actividades del hito) y HU-091 (umbrales y acciones del ítem) no están construidas: solo existen sus tablas del modelo inicial (Plan_Mantenimiento_Actividad y Checklist_Item_Validacion), sin SP, sin pantalla y sin fila en Menus. Sin ellas no hay nada que probar ni documentar. | F23: Dependencia interna | G23: HU-082 y HU-091 · T-4064 a T-4066 y T-4135 a T-4137 | H23: Catalina Pescio | I23: Las seis tareas de prueba, documentación y validación quedan Bloqueada en el Sprint Backlog 4. El equipo acuerda que HU-082 y HU-091 son la primera prioridad del Sprint 5 aunque pertenezcan al 4. | J23: Abierto | L23: =IF($B23="","",IF($J23="Resuelto",IF($K23="","",$K23-$B23),TODAY()-$B23))
A24: 20 | B24: 46322 | C24: Sprint 4 | D24: Bryan Chávez | E24: HU-097 (historial de ejecuciones de una pauta) no está construida: la tabla Checklist_Ocurrencia_Historial existe desde el modelo inicial pero no hay SEL_ que la consulte ni pantalla que la muestre. | F24: Dependencia interna | G24: HU-097 · T-4304 y T-4305 | H24: Catalina Pescio | I24: Las dos tareas quedan Bloqueada. Se arrastran al Sprint 5. | J24: Abierto | L24: =IF($B24="","",IF($J24="Resuelto",IF($K24="","",$K24-$B24),TODAY()-$B24))
A25: 21 | B25: 46322 | C25: Sprint 4 | D25: Bryan Chávez | E25: HU-093 y HU-094 viven solo en la base de datos compartida: cinco SP creados directamente contra el servidor el 21-09-2026 (PUBLICAR_CHECKLIST_VERSION y SEL_CHECKLIST_VERSION a las 19:04; SEL, INS y UPD_CHECKLIST_PROGRAMACION a las 20:13). Ninguno está en un bloque de BD/, ni en la rama EmilioFuentes ni en ninguna otra: se revisó la historia completa del repositorio. Las tres páginas que registran las filas 2212, 2213 y 2214 de Menus (ChecklistVersion.aspx, ChecklistProgramacions.aspx, ChecklistProgramacion.aspx) tampoco existen, y «Programación de pautas» está visible para los siete perfiles: hace 404. | F25: Técnico | G25: HU-093 y HU-094 · T-4197 y T-4198 | H25: Emilio Fuentes | I25: Se le pide a Emilio que suba su rama con los cinco scripts y las tres páginas. Mientras tanto T-4197 y T-4198 siguen Bloqueada. Si no alcanza, la alternativa es extraer las definiciones desde la base a un bloque BD/ y ocultar la fila 2213 de Menus. | J25: Abierto | L25: =IF($B25="","",IF($J25="Resuelto",IF($K25="","",$K25-$B25),TODAY()-$B25))
A26: 22 | L26: =IF($B26="","",IF($J26="Resuelto",IF($K26="","",$K26-$B26),TODAY()-$B26))
A27: 23 | L27: =IF($B27="","",IF($J27="Resuelto",IF($K27="","",$K27-$B27),TODAY()-$B27))
A28: 24 | L28: =IF($B28="","",IF($J28="Resuelto",IF($K28="","",$K28-$B28),TODAY()-$B28))
A29: 25 | L29: =IF($B29="","",IF($J29="Resuelto",IF($K29="","",$K29-$B29),TODAY()-$B29))
A30: 26 | L30: =IF($B30="","",IF($J30="Resuelto",IF($K30="","",$K30-$B30),TODAY()-$B30))
A31: 27 | L31: =IF($B31="","",IF($J31="Resuelto",IF($K31="","",$K31-$B31),TODAY()-$B31))
A32: 28 | L32: =IF($B32="","",IF($J32="Resuelto",IF($K32="","",$K32-$B32),TODAY()-$B32))
A33: 29 | L33: =IF($B33="","",IF($J33="Resuelto",IF($K33="","",$K33-$B33),TODAY()-$B33))
A34: 30 | L34: =IF($B34="","",IF($J34="Resuelto",IF($K34="","",$K34-$B34),TODAY()-$B34))
A35: 31 | L35: =IF($B35="","",IF($J35="Resuelto",IF($K35="","",$K35-$B35),TODAY()-$B35))
A36: 32 | L36: =IF($B36="","",IF($J36="Resuelto",IF($K36="","",$K36-$B36),TODAY()-$B36))
A37: 33 | L37: =IF($B37="","",IF($J37="Resuelto",IF($K37="","",$K37-$B37),TODAY()-$B37))
... A64: 60 | L64: =IF($B64="","",IF($J64="Resuelto",IF($K64="","",$K64-$B64),TODAY()-$B64))

Sheet Instructivo y GitHub
A1: Cómo se usa esta bitácora
A3: Reglas de registro
A4: Elemento | B4: Quién lo completa | C4: Regla
A5: Celdas en amarillo con texto azul | B5: Cada integrante | C5: Son las únicas que se editan. El resto del calendario está precargado y no se modifica.
A6: Qué hice desde el último Daily | B6: Cada integrante | C6: Una o dos líneas, en pasado y con hechos verificables. Se nombra la historia o la tarea, no la actividad genérica: «HU-001 terminada, falta la prueba de bloqueo», no «avancé en login».
A7: Qué haré hasta el próximo Daily | B7: Cada integrante | C7: Compromiso concreto para las próximas veinticuatro horas. Si no cabe en un día, la tarea está mal descompuesta y se divide en el Sprint Backlog.
A8: Impedimentos | B8: Cada integrante | C8: Se escribe «Ninguno» cuando no hay. Cuando hay, se describe en una línea y se copia el mismo día a la hoja Impedimentos con su número.
A9: Historia y Tarea | B9: Cada integrante | C9: Identificadores del Sprint Backlog: HU-xxx y T-xxxx. Permiten cruzar la bitácora con el Sprint Backlog y con el tablero.
A10: Estado en GitHub Projects | B10: Cada integrante | C10: Estado de la tarea en el tablero al momento del Daily. Debe coincidir con lo que muestra GitHub; si no coincide, se corrige el tablero, no la bitácora.
A11: Issue / PR | B11: Cada integrante | C11: Número del issue o del pull request asociado, por ejemplo #42. Es el enlace con el repositorio.
A12: Realizado | B12: Scrum Master | C12: «Sí» cuando la persona participó del Daily. «No» cuando no participó; la celda se marca en rojo y baja el indicador de cumplimiento.
A13: Acuerdo del equipo y próximos pasos | B13: Scrum Master | C13: Se escribe una sola vez por Daily, en la fila de cualquier integrante. Recoge la decisión del equipo, no el resumen de lo dicho.
A15: Equivalencia con GitHub Projects
A16: Estado en el Sprint Backlog | B16: Columna en GitHub Projects | C16: Qué significa
A17: Por hacer | B17: Todo | C17: La tarea está en el Sprint y nadie la ha tomado.
A18: En curso | B18: In Progress | C18: Alguien la tomó y la está construyendo. Una persona no debería tener más de una tarea en este estado.
A19: En revisión | B19: In Review | C19: El pull request está abierto y espera la revisión de otro integrante, según el criterio 7 de la Definition of Done.
A20: Terminada | B20: Done | C20: Cumple los diez criterios de la Definition of Done. No se usa para «terminé de programar».
A21: Bloqueada | B21: Blocked | C21: Existe un impedimento registrado que impide avanzar. Toda tarea en este estado tiene una fila en la hoja Impedimentos.
A23: Ejemplo de un registro completo
A24: Columna | B24: Valor de ejemplo | C24: Comentario
A25: Fecha | B25: 03-09-2026 | C25: Precargada. Segundo Daily del Sprint 1.
A26: Integrante | B26: Bryan Chávez | C26: Precargado: hay una fila por integrante y por Daily.
A27: Qué hice desde el último Daily | B27: Terminé el modelo de datos de HU-001 y dejé el endpoint de autenticación respondiendo en el ambiente de demostración. | C27: Hechos, con la historia identificada.
A28: Qué haré hasta el próximo Daily | B28: T-1003: pantalla de inicio de sesión en la web, con el bloqueo por cinco intentos fallidos. | C28: Compromiso para un día, con la tarea identificada.
A29: Impedimentos | B29: Ninguno | C29: Se escribe «Ninguno» cuando no hay.
A30: Historia | B30: HU-001 | C30: Identificador del Product Backlog.
A31: Tarea | B31: T-1003 | C31: Identificador del Sprint Backlog del Sprint 1.
A32: Estado en GitHub Projects | B32: In Progress | C32: Coincide con la columna del tablero.
A33: Issue / PR | B33: #42 | C33: Enlace con el repositorio.
A34: Realizado | B34: Sí | C34: Lo marca el Scrum Master al cerrar el Daily.
A35: Acuerdo del equipo y próximos pasos | B35: Se adelanta la revisión de permisos al jueves para no bloquear HU-006. | C35: Una sola vez por Daily.
A37: El Daily Scrum dura quince minutos y no es una reunión de estado para la jefatura: es la sincronización del equipo. Si una conversación necesita más tiempo, se anota el acuerdo, se cierra el Daily y esa conversación continúa después con quienes corresponda. El registro se completa durante el Daily o inmediatamente después; una bitácora escrita el viernes de memoria no es evidencia, es reconstrucción.
